project_3_fsm/fsm_2_always.v
// this code is for implemeting a 4 state fsm fr decting sequence 1011 
//using two always blocks each for state transition and output logic

module fsm_2_always (
    input clk,rst,in_bit,
    output reg out
);
parameter S0=2'b00, S1=2'b01, S2=2'b10, S3=2'b11;

reg [1:0] state;

initial begin  //for initializing state and output
    state = S0;
    out = 0;
end

always @(posedge clk or posedge rst) begin:state_transition
    if(rst)
        state <= S0;
    else begin
        case(state)
            S0: state <= in_bit ? S1 : S0;
            S1: state <= in_bit ? S1 : S2;
            S2: state <= in_bit ? S3 : S0;
            S3: state <= in_bit ? S1 : S1;
            default: state <= S0;
        endcase
    end
end

always @(posedge clk) begin:output_logic
    case(state)
        S0: out = in_bit ? 0 : 0;
        S1: out = in_bit ? 0 : 0;
        S2: out = in_bit ? 0 : 0;
        S3: out = in_bit ? 1 : 0;
        default: out = 0;
    endcase
end

endmodule

project_3_fsm/tb_fsm_2_always.v
module tb_fsm_2_always;

reg clk,in_bit,rst;
wire out;

fsm_2_always DUT (.clk(clk),.rst(rst),.in_bit(in_bit),.out(out));

initial begin
    clk = 0;
    rst = 0;
    in_bit = 0;
    // forever #5 clk = ~clk; // Uncomment this line to create a clock signal when simulating
end
/*  REMOVE THE COMMENTS WHEN SIMULATING
initial begin
    $monitor("Time=%0d rst=%b in_bit=%b out=%b",$time,rst,in_bit,out);
    #5 rst = 1; // Assert reset
    #10 rst = 0; // Deassert reset

    // Test sequence: 1,0,1,1 (should detect sequence)
    #10 in_bit = 1;
    #10 in_bit = 0;
    #10 in_bit = 1;
    #10 in_bit = 1;

    // Test sequence: 0,1,0,1 (should not detect sequence)
    #10 in_bit = 0;
    #10 in_bit = 1;
    #10 in_bit = 0;
    #10 in_bit = 1;

    // Test sequence: 1,0,1,1 (should detect sequence again but due to reset it won't be detected)
    #10 in_bit = 1;
    #10 in_bit = 0;
    #10 rst = 1; // Assert reset
    #10 rst = 0; // Deassert reset
    #10 in_bit = 1;
    #10 in_bit = 1;

    #20 $finish; // End simulation
end

initial begin
    $dumpfile("fsm_waveform.vcd");
    $dumpvars(0,tb_fsm_2_always);   
end
*/
endmodule

project_3_fsm/fsm_waveform.vcd
$date
	Thu Oct 23 16:59:15 2025
$end
$version
	Icarus Verilog
$end
$timescale
	1s
$end
$scope module tb_fsm_2_always $end
$var wire 1 ! out $end
$var reg 1 " clk $end
$var reg 1 # in_bit $end
$var reg 1 $ rst $end
$scope module DUT $end
$var wire 1 " clk $end
$var wire 1 # in_bit $end
$var wire 1 $ rst $end
$var parameter 2 % S0 $end
$var parameter 2 & S1 $end
$var parameter 2 ' S2 $end
$var parameter 2 ( S3 $end
$var reg 1 ! out $end
$var reg 2 ) state [1:0] $end
$scope begin output_logic $end
$upscope $end
$scope begin state_transition $end
$upscope $end
$upscope $end
$upscope $end
$enddefinitions $end
$comment Show the parameter values. $end
$dumpall
b11 (
b10 '
b1 &
b0 %
$end
#0
$dumpvars
b0 )
0$
0#
0"
0!
$end
#5
1$
1"
#10
0"
#15
1"
0$
#20
0"
#25
b1 )
1"
1#
#30
0"
#35
b10 )
1"
0#
#40
0"
#45
b11 )
1"
1#
#50
0"
#55
b1 )
1!
1"
#60
0"
#65
b10 )
0!
1"
0#
#70
0"
#75
b11 )
1"
1#
#80
0"
#85
b1 )
1"
0#
#90
0"
#95
1"
1#
#100
0"
#105
1"
#110
0"
#115
b10 )
1"
0#
#120
0"
#125
b0 )
1"
1$
#130
0"
#135
1"
0$
#140
0"
#145
b1 )
1"
1#
