project_2_counter/counter_4bit.v
// This is a 4-bit counter with parametarisations and with asyn reset,enable and load signals.
// This is part of my vlsi learning journey week 2 , project 2.
// notion link:https://www.notion.so/Forge-Quest-Forging-the-4-Bit-Counter-244abc13ad0f80488d05e54697c1ff88?source=copy_link

/* about the project: i am creating a 4 bit counter initially with parameter and it can be implemented for various 
number of bit sizes also. the counter is setted to '0'  when a active low reset signal is used and only will 
count when syncronous enable signal is activated. And when the load is selected the counter value will be loaded
into the output . So the priorirty goes like, asyn reset, load , sync enable , and finally count.  */

// author : chinthala sriram (B.tech 4 th year).



module counter_4bit #(
    parameter width=4
) (
    input clk,rst_n,enable,load,
    input [width-1:0] data_in,
    output [width-1:0] out
);
reg [width-1:0] count = 0;
    always @(posedge clk or negedge rst_n)begin
        if(~rst_n)begin
            count<=0;
        end
        else
            if(load)
                count<=data_in;
            
            else if(enable)begin
                count<=count+1;
            end
    end
    assign out=count;
endmodule

project_2_counter/tb_counter_4bit.v
// this is testbench file for a counter .

module tb_counter_4bit;
localparam width = 4;
reg clk,rst_n,load,enable;
reg [width-1:0] data_in;
wire [width-1:0] out;

counter_4bit #(.width(width)) 
            uut ( .clk(clk),
                .rst_n(rst_n),
                .enable(enable),
                .load(load),
                .data_in(data_in),
                .out(out)
            );
// commenting below block to avoid linting error while simulating remove comments for the below block.
/*
initial begin
    $dumpfile("counter.vcd");  // Name of the waveform file to generate
    $dumpvars(0, tb_counter_4bit); // 'tb_counter_4bit' is testbench module name.
end
*/
initial clk=0;    
always #5 clk=~clk;

initial begin
    // commenting due to avoid linting error , while running uncomment below line.
    //$monitor("time = %0t , enable = %b , rst_n = %b , load = %b , data_in=%d , out = %d",$time,enable,rst_n,load,data_in,out );
    
    enable=1'b1;
    rst_n=1'b1;
    load=1'b0;

    #10 enable=1'b0;
    #10 enable=1'b1;

    #50 rst_n=1'b0;
    #10 rst_n=1'b1;

    

    #100 data_in=4'b1011 ; load=1'b1;
    #10  load=1'b0;
    #100 data_in=4'b1111 ; load=1'b1;
    #10  load=1'b0;
    #10 enable=1'b0;
    #100 data_in=4'b0000 ; load=1'b1;
    #10  load=1'b0;
    #20 enable=1'b1;
    #100 data_in=4'b0011 ; load=1'b0;
    #20 rst_n=1'b0;
    #50 rst_n=1'b1;
#100 $finish;
end
endmodule

project_2_counter/project_2_counter/counter.vcd
$date
	Fri Aug  8 12:50:31 2025
$end
$version
	Icarus Verilog
$end
$timescale
	1s
$end
$scope module tb_counter_4bit $end
$var wire 4 ! out [3:0] $end
$var reg 1 " clk $end
$var reg 4 # data_in [3:0] $end
$var reg 1 $ enable $end
$var reg 1 % load $end
$var reg 1 & rst_n $end
$scope module uut $end
$var wire 1 " clk $end
$var wire 4 ' data_in [3:0] $end
$var wire 1 $ enable $end
$var wire 1 % load $end
$var wire 4 ( out [3:0] $end
$var wire 1 & rst_n $end
$var reg 4 ) count [3:0] $end
$upscope $end
$upscope $end
$enddefinitions $end
#0
$dumpvars
b0 )
b0 (
bx '
1&
0%
1$
bx #
0"
b0 !
$end
#5
b1 !
b1 (
b1 )
1"
#10
0"
0$
#15
1"
#20
0"
1$
#25
b10 !
b10 (
b10 )
1"
#30
0"
#35
b11 !
b11 (
b11 )
1"
#40
0"
#45
b100 !
b100 (
b100 )
1"
#50
0"
#55
b101 !
b101 (
b101 )
1"
#60
0"
#65
b110 !
b110 (
b110 )
1"
#70
b0 !
b0 (
b0 )
0"
0&
#75
1"
#80
0"
1&
#85
b1 !
b1 (
b1 )
1"
#90
0"
#95
b10 !
b10 (
b10 )
1"
#100
0"
#105
b11 !
b11 (
b11 )
1"
#110
0"
#115
b100 !
b100 (
b100 )
1"
#120
0"
#125
b101 !
b101 (
b101 )
1"
#130
0"
#135
b110 !
b110 (
b110 )
1"
#140
0"
#145
b111 !
b111 (
b111 )
1"
#150
0"
#155
b1000 !
b1000 (
b1000 )
1"
#160
0"
#165
b1001 !
b1001 (
b1001 )
1"
#170
0"
#175
b1010 !
b1010 (
b1010 )
1"
#180
0"
1%
b1011 #
b1011 '
#185
b1011 !
b1011 (
b1011 )
1"
#190
0"
0%
#195
b1100 !
b1100 (
b1100 )
1"
#200
0"
#205
b1101 !
b1101 (
b1101 )
1"
#210
0"
#215
b1110 !
b1110 (
b1110 )
1"
#220
0"
#225
b1111 !
b1111 (
b1111 )
1"
#230
0"
#235
b0 !
b0 (
b0 )
1"
#240
0"
#245
b1 !
b1 (
b1 )
1"
#250
0"
#255
b10 !
b10 (
b10 )
1"
#260
0"
#265
b11 !
b11 (
b11 )
1"
#270
0"
#275
b100 !
b100 (
b100 )
1"
#280
0"
#285
b101 !
b101 (
b101 )
1"
#290
0"
1%
b1111 #
b1111 '
#295
b1111 !
b1111 (
b1111 )
1"
#300
0"
0%
#305
b0 !
b0 (
b0 )
1"
#310
0"
0$
#315
1"
#320
0"
#325
1"
#330
0"
#335
1"
#340
0"
#345
1"
#350
0"
#355
1"
#360
0"
#365
1"
#370
0"
#375
1"
#380
0"
#385
1"
#390
0"
#395
1"
#400
0"
#405
1"
#410
0"
1%
b0 #
b0 '
#415
1"
#420
0"
0%
#425
1"
#430
0"
#435
1"
#440
0"
1$
#445
b1 !
b1 (
b1 )
1"
#450
0"
#455
b10 !
b10 (
b10 )
1"
#460
0"
#465
b11 !
b11 (
b11 )
1"
#470
0"
#475
b100 !
b100 (
b100 )
1"
#480
0"
#485
b101 !
b101 (
b101 )
1"
#490
0"
#495
b110 !
b110 (
b110 )
1"
#500
0"
#505
b111 !
b111 (
b111 )
1"
#510
0"
#515
b1000 !
b1000 (
b1000 )
1"
#520
0"
#525
b1001 !
b1001 (
b1001 )
1"
#530
0"
#535
b1010 !
b1010 (
b1010 )
1"
#540
0"
b11 #
b11 '
#545
b1011 !
b1011 (
b1011 )
1"
#550
0"
#555
b1100 !
b1100 (
b1100 )
1"
#560
b0 !
b0 (
b0 )
0"
0&
#565
1"
#570
0"
#575
1"
#580
0"
#585
1"
#590
0"
#595
1"
#600
0"
#605
1"
#610
0"
1&
#615
b1 !
b1 (
b1 )
1"
#620
0"
#625
b10 !
b10 (
b10 )
1"
#630
0"
#635
b11 !
b11 (
b11 )
1"
#640
0"
#645
b100 !
b100 (
b100 )
1"
#650
0"
#655
b101 !
b101 (
b101 )
1"
#660
0"
#665
b110 !
b110 (
b110 )
1"
#670
0"
#675
b111 !
b111 (
b111 )
1"
#680
0"
#685
b1000 !
b1000 (
b1000 )
1"
#690
0"
#695
b1001 !
b1001 (
b1001 )
1"
#700
0"
#705
b1010 !
b1010 (
b1010 )
1"
