SOC_APB_interconnect_verilog/apb_master.v
`timescale 1ns / 1ps

module apb_master (
    // ------------------------------------------------------------------------
    // Clock and Reset
    // ------------------------------------------------------------------------
    input  wire        PCLK,
    input  wire        PRESETn,

    // ------------------------------------------------------------------------
    // Application Interface (From your CPU/Interconnect)
    // ------------------------------------------------------------------------
    input  wire        req_start,   // Pulse HIGH to start transaction
    input  wire        req_write,   // 1 = Write, 0 = Read
    input  wire [31:0] req_addr,
    input  wire [31:0] req_data,
    output reg         req_done,    // Pulses HIGH for 1 cycle when finished
    output reg  [31:0] req_rdata,   // Data read from slave

    // ------------------------------------------------------------------------
    // AMBA 3 APB Bus Interface (To Interconnect/Slaves)
    // ------------------------------------------------------------------------
    output reg         PSEL,
    output reg         PENABLE,
    output reg         PWRITE,
    output reg  [31:0] PADDR,
    output reg  [31:0] PWDATA,
    input  wire        PREADY,
    input  wire [31:0] PRDATA,
    input  wire        PSLVERR      // Ignored in this basic implementation
);

    localparam [1:0] 
        IDLE   = 2'b00,
        SETUP  = 2'b01,
        ACCESS = 2'b10;

    reg [1:0] current_state, next_state;

    // ========================================================================
    // COMBINATIONAL BLOCK: Next State Logic
    // ========================================================================
    always @(*) begin
        next_state = current_state; 

        case (current_state)
            IDLE: begin
                if (req_start) next_state = SETUP;
                else           next_state = IDLE;
            end

            SETUP: begin
                next_state = ACCESS; // Unconditional transition
            end

            ACCESS: begin
                if (PREADY) begin
                    if (req_start) next_state = SETUP; // Back-to-back transfer
                    else           next_state = IDLE;  // Transaction complete
                end else begin
                    next_state = ACCESS;               // Wait states
                end
            end

            default: next_state = IDLE;
        endcase
    end

    // ========================================================================
    // SEQUENTIAL BLOCK: Handshakes and Look-Ahead Bus Outputs
    // ========================================================================
    always @(posedge PCLK or negedge PRESETn) begin
        if (!PRESETn) begin
            current_state <= IDLE;
            PSEL          <= 1'b0;
            PENABLE       <= 1'b0;
            PWRITE        <= 1'b0;
            PADDR         <= 32'h00000000;
            PWDATA        <= 32'h00000000;
            req_done      <= 1'b0;
            req_rdata     <= 32'h00000000;
        end else begin
            // 1. Advance State
            current_state <= next_state;

            // 2. Handshake & Read Logic (Based on Current State)
            if (current_state == ACCESS && PREADY) begin
                req_done <= 1'b1;
                if (!PWRITE) begin
                    req_rdata <= PRDATA; // Capture read data
                end
            end else begin
                req_done <= 1'b0;
            end

            // 3. APB Bus Output Logic (Based on Next State for glitch-free routing)
            case (next_state)
                IDLE: begin
                    PSEL    <= 1'b0;
                    PENABLE <= 1'b0;
                end
                
                SETUP: begin
                    PSEL    <= 1'b1;
                    PENABLE <= 1'b0;         
                    PWRITE  <= req_write;    // Dynamic read/write control
                    PADDR   <= req_addr;     
                    PWDATA  <= req_data;     
                end
                
                ACCESS: begin
                    PENABLE <= 1'b1;         
                    // PSEL, PADDR, PWDATA, PWRITE maintain stable values
                end
            endcase
        end
    end

endmodule

SOC_APB_interconnect_verilog/tb_apb_master.v
`timescale 1ns / 1ps

module tb_apb_master;

    // 1. TB Signals
    reg         PCLK;
    reg         PRESETn;
    
    // Application Side
    reg         req_start;
    reg         req_write;
    reg  [31:0] req_addr;
    reg  [31:0] req_data;
    wire        req_done;
    wire [31:0] req_rdata;
    
    // APB Bus Side
    wire        PSEL;
    wire        PENABLE;
    wire        PWRITE;
    wire [31:0] PADDR;
    wire [31:0] PWDATA;
    reg         PREADY;
    reg  [31:0] PRDATA;
    reg         PSLVERR;

    // 2. Instantiate DUT
    apb_master uut (
        .PCLK(PCLK),
        .PRESETn(PRESETn),
        .req_start(req_start),
        .req_write(req_write),
        .req_addr(req_addr),
        .req_data(req_data),
        .req_done(req_done),
        .req_rdata(req_rdata),
        .PSEL(PSEL),
        .PENABLE(PENABLE),
        .PWRITE(PWRITE),
        .PADDR(PADDR),
        .PWDATA(PWDATA),
        .PREADY(PREADY),
        .PRDATA(PRDATA),
        .PSLVERR(PSLVERR)
    );

    // 3. Clock Gen (10ns -> 100MHz)
    always #5 PCLK = ~PCLK;

    // 4. Test Sequence
    initial begin
        $dumpfile("apb_master_waves.vcd");
        $dumpvars(0, tb_apb_master);

        // Initialize
        PCLK      = 0;
        PRESETn   = 0;
        req_start = 0;
        req_write = 0;
        req_addr  = 0;
        req_data  = 0;
        PREADY    = 0;
        PRDATA    = 0;
        PSLVERR   = 0;

        // Reset system
        #15 PRESETn = 1;

        // ==========================================
        // TEST 1: WRITE (With 1 Wait State)
        // ==========================================
        @(posedge PCLK); 
        req_start = 1;
        req_write = 1;
        req_addr  = 32'hAAAA_BBBB;
        req_data  = 32'hDEAD_BEEF;

        @(posedge PCLK);
        req_start = 0; // Master in SETUP
        PREADY    = 0; // Slave not ready yet

        @(posedge PCLK);
        // Master in ACCESS (Wait State 1)
        PREADY    = 1; // Slave is now ready

        @(posedge PCLK);
        // Transaction finishes
        PREADY    = 0;

        #20; // Idle gap

        // ==========================================
        // TEST 2: READ (0 Wait States)
        // ==========================================
        @(posedge PCLK); 
        req_start = 1;
        req_write = 0; // 0 for READ
        req_addr  = 32'h1111_2222;

        @(posedge PCLK);
        req_start = 0; // Master in SETUP

        @(posedge PCLK);
        // Master in ACCESS
        PREADY    = 1; 
        PRDATA    = 32'hCAFE_F00D; // Slave provides data

        @(posedge PCLK);
        PREADY    = 0;

        #30;
        $finish;
    end

endmodule

SOC_APB_interconnect_verilog/apb_master_waves.vcd
$date
	Mon Apr  6 23:37:25 2026
$end
$version
	Icarus Verilog
$end
$timescale
	1ps
$end
$scope module tb_apb_master $end
$var wire 32 ! req_rdata [31:0] $end
$var wire 1 " req_done $end
$var wire 1 # PWRITE $end
$var wire 32 $ PWDATA [31:0] $end
$var wire 1 % PSEL $end
$var wire 1 & PENABLE $end
$var wire 32 ' PADDR [31:0] $end
$var reg 1 ( PCLK $end
$var reg 32 ) PRDATA [31:0] $end
$var reg 1 * PREADY $end
$var reg 1 + PRESETn $end
$var reg 1 , PSLVERR $end
$var reg 32 - req_addr [31:0] $end
$var reg 32 . req_data [31:0] $end
$var reg 1 / req_start $end
$var reg 1 0 req_write $end
$scope module uut $end
$var wire 1 ( PCLK $end
$var wire 32 1 PRDATA [31:0] $end
$var wire 1 * PREADY $end
$var wire 1 + PRESETn $end
$var wire 1 , PSLVERR $end
$var wire 32 2 req_addr [31:0] $end
$var wire 32 3 req_data [31:0] $end
$var wire 1 / req_start $end
$var wire 1 0 req_write $end
$var parameter 2 4 ACCESS $end
$var parameter 2 5 IDLE $end
$var parameter 2 6 SETUP $end
$var reg 32 7 PADDR [31:0] $end
$var reg 1 & PENABLE $end
$var reg 1 % PSEL $end
$var reg 32 8 PWDATA [31:0] $end
$var reg 1 # PWRITE $end
$var reg 2 9 current_state [1:0] $end
$var reg 2 : next_state [1:0] $end
$var reg 1 " req_done $end
$var reg 32 ; req_rdata [31:0] $end
$upscope $end
$upscope $end
$enddefinitions $end
$comment Show the parameter values. $end
$dumpall
b1 6
b0 5
b10 4
$end
#0
$dumpvars
b0 ;
b0 :
b0 9
b0 8
b0 7
b0 3
b0 2
b0 1
00
0/
b0 .
b0 -
0,
0+
0*
b0 )
0(
b0 '
0&
0%
b0 $
0#
0"
b0 !
$end
#5000
1(
#10000
0(
#15000
b1 :
b11011110101011011011111011101111 .
b11011110101011011011111011101111 3
b10101010101010101011101110111011 -
b10101010101010101011101110111011 2
10
1/
1(
1+
#20000
0(
#25000
b11011110101011011011111011101111 $
b11011110101011011011111011101111 8
b10101010101010101011101110111011 '
b10101010101010101011101110111011 7
1#
1%
b1 9
b10 :
0/
1(
#30000
0(
#35000
1&
b10 9
b0 :
1*
1(
#40000
0(
#45000
0&
0%
b0 9
b0 :
0*
1(
#50000
0(
#55000
1(
#60000
0(
#65000
b1 :
b10001000100010010001000100010 -
b10001000100010010001000100010 2
00
1/
1(
#70000
0(
#75000
b10001000100010010001000100010 '
b10001000100010010001000100010 7
0#
1%
b1 9
b10 :
0/
1(
#80000
0(
#85000
1&
b10 9
b0 :
b11001010111111101111000000001101 )
b11001010111111101111000000001101 1
1*
1(
#90000
0(
#95000
0&
0%
b0 9
b0 :
0*
1(
