project_4_parametarized_ALU/RTL/shifter_unit.v
module shifter #(
    parameter DATA_WIDTH = 8,
    parameter SHIFT_AMOUNT_WIDTH = $clog2(DATA_WIDTH)
) (
    input signed [DATA_WIDTH-1:0] data,
    input [SHIFT_AMOUNT_WIDTH-1:0] shift_amount,
    input [1:0] shift_op,
    output reg [DATA_WIDTH-1:0] result
);
    always @(*) begin
        case (shift_op)
            2'b00: result = data << shift_amount;  // SLL
            2'b01: result = data >> shift_amount;  // SRL
            2'b10: result = data >>> shift_amount; // SRA
            default: result = data;
        endcase
    end
endmodule

logic_unit.v
module logic_unit #(
    parameter DATA_WIDTH = 8
) (
    input [DATA_WIDTH-1:0] a, b,
    input [2:0] logic_op,
    output  reg [DATA_WIDTH-1:0] result
);
    always @(*) begin
        case (logic_op)
            3'b000: result = a & b;      // AND
            3'b001: result = a | b;      // OR
            3'b010: result = a ^ b;      // XOR
            3'b011: result = ~a;         // NOT
            3'b100: result = ~(a & b);   // NAND
            3'b101: result = ~(a | b);    // NOR
            3'b110 : result = ~(a ^ b);   // XNOR
            default: result = {DATA_WIDTH{1'b0}};
        endcase
    end
endmodule

project_4_parametarized_ALU/RTL/arithmetic_unit.v
module arithmetic_unit #(
    parameter DATA_WIDTH = 8
) (
    input [DATA_WIDTH-1:0] a, b,
    input [2:0] arith_op,
    output reg [DATA_WIDTH-1:0] result,
    output reg carry_out,
    output reg [2*DATA_WIDTH-1:0] mult_result
);

    wire [DATA_WIDTH:0] add_result, sub_result;
    
    // Addition: capture 9-bit result to detect carry
    assign add_result = a + b;
    
    // Subtraction: use two's complement (a - b = a + ~b + 1)
    assign sub_result = a - b;
    
    always @(*) begin
        case (arith_op)
            3'b000: begin
                result = add_result[DATA_WIDTH-1:0];  // 8-bit result
                carry_out = add_result[DATA_WIDTH];    // Carry flag
            end
            3'b001: begin
                result = sub_result[DATA_WIDTH-1:0];
                carry_out = sub_result[DATA_WIDTH];
            end
            3'b010: begin
                result = a + 1;  // INC
                carry_out = (a == {DATA_WIDTH{1'b1}});
            end
            3'b011: begin
                result = a - 1;  // DEC
                carry_out = (a == {DATA_WIDTH{1'b0}});
            end
            3'b100: begin 
                mult_result = a * b; // MUL: 2*data width -bit result
                carry_out=1'b0;
            end
                         
            default: begin
                result = {DATA_WIDTH{1'b0}};
                carry_out = 1'b0;
            end
        endcase
    end
endmodule

project_4_parametarized_ALU/RTL/alu.v
// parameterized ALU Top module

module alu #(
    parameter DATA_WIDTH = 8,
    parameter SHIFT_BITS = $clog2(DATA_WIDTH)
) (
    input [DATA_WIDTH-1:0] a,                    
    input [DATA_WIDTH-1:0] b,                    
    input [4:0] opcode,
    input [SHIFT_BITS-1:0] shift_amount,
    
    output reg [DATA_WIDTH-1:0] result,          
    output reg carry_out,
    output reg [2*DATA_WIDTH-1:0] mult_result
);

    // Internal signals
    wire [DATA_WIDTH-1:0] arith_result;
    wire arith_carry;
    wire [2*DATA_WIDTH-1:0] arith_mult_result;
    
    wire [DATA_WIDTH-1:0] logic_result;
    
    wire [DATA_WIDTH-1:0] shift_result;
    
    wire [1:0] unit_select = opcode[4:3];
    wire [2:0] unit_opcode = opcode[2:0];
    
    //ARITHEMATIC UNIT
    
    arithmetic_unit #(.DATA_WIDTH(DATA_WIDTH)) arith_inst (
        .a(a),
        .b(b),
        .arith_op(unit_opcode),
        .result(arith_result),
        .carry_out(arith_carry),
        .mult_result(arith_mult_result)
    );
    
    // LOGIC UNIT 

    logic_unit #(.DATA_WIDTH(DATA_WIDTH)) logic_inst (
        .a(a),
        .b(b),
        .logic_op(unit_opcode),
        .result(logic_result)
    );
       
    // SHIFTER UNIT 

    shifter #(
        .DATA_WIDTH(DATA_WIDTH),
        .SHIFT_AMOUNT_WIDTH(SHIFT_BITS)
    ) shifter_inst (
        .data(a),              // Passed only the first operand 'a' for shifting
        .shift_amount(shift_amount),
        .shift_op(unit_opcode[1:0]),
        .result(shift_result)
    );
    
    // ============================================================
    // MULTIPLEXER: SELECT OUTPUT BASED ON UNIT
    // ============================================================
    
    always @(*) begin
        case (unit_select)
            2'b00: begin  // ARITHMETIC UNIT
                result = arith_result;
                carry_out = arith_carry;
                mult_result = arith_mult_result;
            end
            
            2'b01: begin  // LOGIC UNIT
                result = logic_result;
                carry_out = 1'b0;
                mult_result = {2*DATA_WIDTH{1'b0}};
            end
            
            2'b10: begin  // SHIFTER UNIT
                result = shift_result;
                carry_out = 1'b0;
                mult_result = {2*DATA_WIDTH{1'b0}};
            end
            
            2'b11: begin  // RESERVED
                result = {DATA_WIDTH{1'b0}};
                carry_out = 1'b0;
                mult_result = {2*DATA_WIDTH{1'b0}};
            end
            default: begin
                result = {DATA_WIDTH{1'b0}};
                carry_out = 1'b0;
                mult_result = {2*DATA_WIDTH{1'b0}};
            end
        endcase
    end
    
endmodule

project_4_parametarized_ALU/tb_alu.v
module tb_alu;
    parameter DATA_WIDTH = 32;
    parameter SHIFT_BITS = $clog2(DATA_WIDTH); // $clog2(32) = 5
    
    reg [DATA_WIDTH-1:0] a, b;
    reg [4:0] opcode;
    reg [SHIFT_BITS-1:0] shift_amount;
    wire [DATA_WIDTH-1:0] result;
    wire carry_out;
    wire [2*DATA_WIDTH-1:0] mult_result; // 64 bits

    // Max 32-bit value
    localparam MAX_32 = 32'hFFFF_FFFF; // 4294967295
    localparam HALF_32 = 32'h8000_0000; // 2147483648
    
    // Instantiate ALU
    alu #(.DATA_WIDTH(DATA_WIDTH), .SHIFT_BITS(SHIFT_BITS)) uut (
        .a(a), .b(b), .opcode(opcode), .shift_amount(shift_amount),
        .result(result), .carry_out(carry_out), .mult_result(mult_result)
    );
    
    integer test_count = 0;
    integer pass_count = 0;
    integer fail_count = 0;
    
    // Task for regular operations (ADD, SUB, INC, DEC, AND, OR, XOR, etc.)
    task run_test;
        input [DATA_WIDTH-1:0] test_a;
        input [DATA_WIDTH-1:0] test_b;
        input [4:0] test_opcode;
        input [SHIFT_BITS-1:0] test_shift;
        input [DATA_WIDTH-1:0] exp_result;
        input exp_carry;
        input [132:0] test_name;
        
        begin
            test_count = test_count + 1;
            a = test_a;
            b = test_b;
            opcode = test_opcode;
            shift_amount = test_shift;
            #10;
            
            if (result == exp_result && carry_out == exp_carry) begin
                $display("[PASS %3d] %-20s | a=%10d, b=%10d, shift=%d | result=%10d, carry=%b", 
                         test_count, test_name, test_a, test_b, test_shift, result, carry_out);
                pass_count = pass_count + 1;
            end else begin
                $display("[FAIL %3d] %-20s | a=%10d, b=%10d, shift=%d | Got: result=%10d, carry=%b | Exp: result=%10d, carry=%b", 
                         test_count, test_name, test_a, test_b, test_shift, result, carry_out, exp_result, exp_carry);
                fail_count = fail_count + 1;
            end
        end
    endtask
    
    // Task for MUL operations (verifies mult_result output)
    task run_test_mul;
        input [DATA_WIDTH-1:0] test_a;
        input [DATA_WIDTH-1:0] test_b;
        input [2*DATA_WIDTH-1:0] exp_mult_result;
        input [31:0] test_name;
        
        begin
            test_count = test_count + 1;
            a = test_a;
            b = test_b;
            opcode = 5'b00_100;  // MUL opcode
            shift_amount = 5'b00000;
            #10;
            
            if (mult_result == exp_mult_result) begin
                $display("[PASS %3d] %-20s | a=%10d, b=%10d | mult_result=%20d", 
                         test_count, test_name, test_a, test_b, mult_result);
                pass_count = pass_count + 1;
            end else begin
                $display("[FAIL %3d] %-20s | a=%10d, b=%10d | Got mult_result=%20d | Expected: %20d", 
                         test_count, test_name, test_a, test_b, mult_result, exp_mult_result);
                fail_count = fail_count + 1;
            end
        end
    endtask
    
    initial begin
        $display("\n");
        $display("╔══════════════════════════════════════════════════════════════════════╗");
        $display("║       COMPREHENSIVE ALU TEST SUITE (DATA_WIDTH = %d bits)            ║", DATA_WIDTH);
        $display("╚══════════════════════════════════════════════════════════════════════╝\n");
        
        
        // ================================================================
        // ARITHMETIC UNIT TESTS (opcode[4:3] = 2'b00)
        // ================================================================
        
        $display("═══════════════════════════════════════════════════════════════════════");
        $display("ARITHMETIC UNIT TESTS (Opcode 5'b00_XXX)");
        $display("═══════════════════════════════════════════════════════════════════════\n");
        
        // ─────────────────────────────────────────────────────────────
        // ADD Tests (opcode = 5'b00_000)
        // ─────────────────────────────────────────────────────────────
        $display("--- ADD OPERATION (5'b00_000) ---");
        run_test(32'd1000000000, 32'd2000000000, 5'b00_000, 5'b00000, 32'd3000000000, 1'b0, "ADD: Normal");
        run_test(HALF_32,        HALF_32,        5'b00_000, 5'b00000, 32'd0,          1'b1, "ADD: Overflow Mid");
        run_test(MAX_32,         32'd1,          5'b00_000, 5'b00000, 32'd0,          1'b1, "ADD: Max+1");
        run_test(MAX_32,         MAX_32,         5'b00_000, 5'b00000, 32'd4294967294, 1'b1, "ADD: Max+Max");
        
        // ─────────────────────────────────────────────────────────────
        // SUB Tests (opcode = 5'b00_001)
        // ─────────────────────────────────────────────────────────────
        $display("\n--- SUB OPERATION (5'b00_001) ---");
        run_test(32'd3000000000, 32'd1000000000, 5'b00_001, 5'b00000, 32'd2000000000, 1'b0, "SUB: Normal");
        run_test(32'd10000,      32'd20000,      5'b00_001, 5'b00000, 32'd4294957296, 1'b1, "SUB: Underflow");
        run_test(MAX_32,         32'd1,          5'b00_001, 5'b00000, 32'd4294967294, 1'b0, "SUB: Max-1");
        run_test(32'd0,          32'd1,          5'b00_001, 5'b00000, MAX_32,         1'b1, "SUB: 0-1");
        
        // ─────────────────────────────────────────────────────────────
        // INC Tests (opcode = 5'b00_010)
        // ─────────────────────────────────────────────────────────────
        $display("\n--- INC OPERATION (5'b00_010) ---");
        run_test(MAX_32, 32'd0, 5'b00_010, 5'b00000, 32'd0,            1'b1, "INC: Max");
        run_test(32'd1000000000, 32'd0, 5'b00_010, 5'b00000, 32'd1000000001, 1'b0, "INC: Normal");
        
        // ─────────────────────────────────────────────────────────────
        // DEC Tests (opcode = 5'b00_011)
        // ─────────────────────────────────────────────────────────────
        $display("\n--- DEC OPERATION (5'b00_011) ---");
        run_test(32'd0, 32'd0, 5'b00_011, 5'b00000, MAX_32,         1'b1, "DEC: Zero");
        run_test(32'd1000000000, 32'd0, 5'b00_011, 5'b00000, 32'd999999999, 1'b0, "DEC: Normal");
        
        // ─────────────────────────────────────────────────────────────
        // MUL Tests (opcode = 5'b00_100) - USING MUL TASK
        // ─────────────────────────────────────────────────────────────
        $display("\n--- MUL OPERATION (5'b00_100) ---");
        run_test_mul(32'd100000, 32'd10000, 64'd1000000000,          "MUL: 1e5 * 1e4");
        run_test_mul(32'd50000, 32'd50000, 64'd2500000000,           "MUL: 5e4 * 5e4");
        run_test_mul(32'd65536, 32'd65536, 64'd4294967296,           "MUL: 2^16 * 2^16");
        run_test_mul(32'd2,     32'd2147483647, 64'd4294967294,      "MUL: 2 * (Max/2)");
        
        // ================================================================
        // LOGIC UNIT TESTS (opcode[4:3] = 2'b01)
        // ================================================================
        
        $display("\n═══════════════════════════════════════════════════════════════════════");
        $display("LOGIC UNIT TESTS (Opcode 5'b01_XXX)");
        $display("═══════════════════════════════════════════════════════════════════════\n");
        
        // ─────────────────────────────────────────────────────────────
        // AND Tests (opcode = 5'b01_000)
        // ─────────────────────────────────────────────────────────────
        $display("--- AND OPERATION (5'b01_000) ---");
        run_test(32'hFFFF0000, 32'h0000FFFF, 5'b01_000, 5'b00000, 32'h00000000, 1'b0, "AND: Disjoint");
        run_test(32'hAAAA_AAAA, 32'h5555_5555, 5'b01_000, 5'b00000, 32'h0000_0000, 1'b0, "AND: Complement");
        
        // ─────────────────────────────────────────────────────────────
        // OR Tests (opcode = 5'b01_001)
        // ─────────────────────────────────────────────────────────────
        $display("\n--- OR OPERATION (5'b01_001) ---");
        run_test(32'hFFFF0000, 32'h0000FFFF, 5'b01_001, 5'b00000, 32'hFFFFFFFF, 1'b0, "OR: Combine");
        
        // ─────────────────────────────────────────────────────────────
        // XOR Tests (opcode = 5'b01_010)
        // ─────────────────────────────────────────────────────────────
        $display("\n--- XOR OPERATION (5'b01_010) ---");
        run_test(32'hFFFF0000, 32'hFFFF0000, 5'b01_010, 5'b00000, 32'h00000000, 1'b0, "XOR: Same");
        
        // ─────────────────────────────────────────────────────────────
        // NOT Tests (opcode = 5'b01_011)
        // ─────────────────────────────────────────────────────────────
        $display("\n--- NOT OPERATION (5'b01_011) ---");
        run_test(32'hF0F0F0F0, 32'd0, 5'b01_011, 5'b00000, 32'h0F0F0F0F, 1'b0, "NOT: Pattern");
        
        // ─────────────────────────────────────────────────────────────
        // NAND Tests (opcode = 5'b01_100)
        // ─────────────────────────────────────────────────────────────
        $display("\n--- NAND OPERATION (5'b01_100) ---");
        run_test(32'hFFFF0000, 32'h0000FFFF, 5'b01_100, 5'b00000, 32'hFFFFFFFF, 1'b0, "NAND: Disjoint");
        
        // ─────────────────────────────────────────────────────────────
        // NOR Tests (opcode = 5'b01_101)
        // ─────────────────────────────────────────────────────────────
        $display("\n--- NOR OPERATION (5'b01_101) ---");
        run_test(32'hFFFF0000, 32'h0000FFFF, 5'b01_101, 5'b00000, 32'h00000000, 1'b0, "NOR: Combine");
        
        // ─────────────────────────────────────────────────────────────
        // XNOR Tests (opcode = 5'b01_110)
        // ─────────────────────────────────────────────────────────────
        $display("\n--- XNOR OPERATION (5'b01_110) ---");
        run_test(32'hAAAA_AAAA, 32'h5555_5555, 5'b01_110, 5'b00000, 32'h0000_0000, 1'b0, "XNOR: Complement");
        
        // ================================================================
        // SHIFTER UNIT TESTS (opcode[4:3] = 2'b10)
        // ================================================================
        
        $display("\n═══════════════════════════════════════════════════════════════════════");
        $display("SHIFTER UNIT TESTS (Opcode 5'b10_XXX)");
        $display("═══════════════════════════════════════════════════════════════════════\n");
        
        // ─────────────────────────────────────────────────────────────
        // SLL Tests (opcode = 5'b10_000, shift_op = 2'b00)
        // ─────────────────────────────────────────────────────────────
        $display("--- SLL OPERATION (5'b10_000) - Shift Left Logical ---");
        run_test(32'h00000001, 32'd0, 5'b10_000, 5'd31, 32'h80000000, 1'b0, "SLL: Shift 31");
        run_test(32'h80000000, 32'd0, 5'b10_000, 5'd1, 32'h00000000, 1'b0, "SLL: MSB Out");
        
        // ─────────────────────────────────────────────────────────────
        // SRL Tests (opcode = 5'b10_001, shift_op = 2'b01)
        // ─────────────────────────────────────────────────────────────
        $display("\n--- SRL OPERATION (5'b10_001) - Shift Right Logical ---");
        run_test(32'h80000000, 32'd0, 5'b10_001, 5'd1, 32'h40000000, 1'b0, "SRL: Normal 1");
        run_test(32'h80000000, 32'd0, 5'b10_001, 5'd31, 32'h00000001, 1'b0, "SRL: Shift 31");
        
        // ─────────────────────────────────────────────────────────────
        // SRA Tests (opcode = 5'b10_010, shift_op = 2'b10)
        // ─────────────────────────────────────────────────────────────
        $display("\n--- SRA OPERATION (5'b10_010) - Shift Right Arithmetic ---");
        run_test(32'h80000000, 32'd0, 5'b10_010, 5'd1, 32'hC0000000, 1'b0, "SRA: Max neg >> 1"); // -2^31 >> 1 = -2^30
        run_test(32'hF0000000, 32'd0, 5'b10_010, 5'd4, 32'hFF000000, 1'b0, "SRA: Negative 4");
        run_test(32'h80000000, 32'd0, 5'b10_010, 5'd31, 32'hFFFFFFFF, 1'b0, "SRA: Neg to -1");
        
        // ================================================================
        // FLAG VERIFICATION TESTS
        // ================================================================
        
        $display("\n═══════════════════════════════════════════════════════════════════════");
        $display("FLAG VERIFICATION TESTS");
        $display("═══════════════════════════════════════════════════════════════════════\n");
        
        $display("--- Carry Flag Tests ---");
        run_test(MAX_32, 32'd1,  5'b00_000, 5'b00000, 32'd0,     1'b1, "Carry from ADD");
        run_test(32'd0,  32'd1,  5'b00_011, 5'b00000, MAX_32,    1'b1, "Carry from DEC (Borrow)");
        
        $display("\n--- No Carry Tests (Logic, Shifter) ---");
        run_test(32'hFFFFFFFF, 32'd0, 5'b01_011, 5'b00000, 32'h00000000, 1'b0, "Logic: No carry");
        run_test(32'hAAAA_AAAA, 32'd0, 5'b10_000, 5'd10, 32'hAAAAA800, 1'b0, "Shifter: No carry");
        
        // ================================================================
        // TEST SUMMARY
        // ================================================================
        
        $display("\n═══════════════════════════════════════════════════════════════════════");
        $display("╔══════════════════════════════════════════════════════════════════════╗");
        $display("║                           TEST SUMMARY                               ║");
        $display("╠══════════════════════════════════════════════════════════════════════╣");
        $display("║ Total Tests:       %3d                                               ║", test_count);
        $display("║ Passed:            %3d                                               ║", pass_count);
        $display("║ Failed:            %3d                                               ║", fail_count);
        if (test_count > 0)
            $display("║ Success Rate:      %6.2f%%                                            ║", (pass_count * 100.0) / test_count);
        $display("╚══════════════════════════════════════════════════════════════════════╝\n");
        
        if (fail_count == 0) begin
            $display("✓ ALL TESTS PASSED - ALU DESIGN VERIFIED!");
        end else begin
            $display("✗ %d TESTS FAILED - REVIEW DESIGN", fail_count);
        end
        
        $display("\n");
        $finish;
    end
    
endmodule

project_4_parametarized_ALU/sim_wave/tb_alu.vcd
$date
	Thu Nov 20 14:01:25 2025
$end
$version
	Icarus Verilog
$end
$timescale
	1s
$end
$scope module tb_alu $end
$var wire 32 ! result [31:0] $end
$var wire 64 " mult_result [63:0] $end
$var wire 1 # carry_out $end
$var parameter 32 $ DATA_WIDTH $end
$var parameter 32 % HALF_32 $end
$var parameter 32 & MAX_32 $end
$var parameter 32 ' SHIFT_BITS $end
$var reg 32 ( a [31:0] $end
$var reg 32 ) b [31:0] $end
$var reg 5 * opcode [4:0] $end
$var reg 5 + shift_amount [4:0] $end
$var integer 32 , fail_count [31:0] $end
$var integer 32 - pass_count [31:0] $end
$var integer 32 . test_count [31:0] $end
$scope module uut $end
$var wire 32 / a [31:0] $end
$var wire 32 0 b [31:0] $end
$var wire 5 1 opcode [4:0] $end
$var wire 5 2 shift_amount [4:0] $end
$var wire 2 3 unit_select [1:0] $end
$var wire 3 4 unit_opcode [2:0] $end
$var wire 32 5 shift_result [31:0] $end
$var wire 32 6 logic_result [31:0] $end
$var wire 32 7 arith_result [31:0] $end
$var wire 64 8 arith_mult_result [63:0] $end
$var wire 1 9 arith_carry $end
$var parameter 32 : DATA_WIDTH $end
$var parameter 32 ; SHIFT_BITS $end
$var reg 1 # carry_out $end
$var reg 64 < mult_result [63:0] $end
$var reg 32 = result [31:0] $end
$scope module arith_inst $end
$var wire 32 > a [31:0] $end
$var wire 3 ? arith_op [2:0] $end
$var wire 32 @ b [31:0] $end
$var wire 33 A sub_result [32:0] $end
$var wire 33 B add_result [32:0] $end
$var parameter 32 C DATA_WIDTH $end
$var reg 1 9 carry_out $end
$var reg 64 D mult_result [63:0] $end
$var reg 32 E result [31:0] $end
$upscope $end
$scope module logic_inst $end
$var wire 32 F a [31:0] $end
$var wire 32 G b [31:0] $end
$var wire 3 H logic_op [2:0] $end
$var parameter 32 I DATA_WIDTH $end
$var reg 32 J result [31:0] $end
$upscope $end
$scope module shifter_inst $end
$var wire 32 K data [31:0] $end
$var wire 5 L shift_amount [4:0] $end
$var wire 2 M shift_op [1:0] $end
$var parameter 32 N DATA_WIDTH $end
$var parameter 32 O SHIFT_AMOUNT_WIDTH $end
$var reg 32 P result [31:0] $end
$upscope $end
$upscope $end
$scope task run_test $end
$var reg 1 Q exp_carry $end
$var reg 32 R exp_result [31:0] $end
$var reg 32 S test_a [31:0] $end
$var reg 32 T test_b [31:0] $end
$var reg 133 U test_name [132:0] $end
$var reg 5 V test_opcode [4:0] $end
$var reg 5 W test_shift [4:0] $end
$upscope $end
$scope task run_test_mul $end
$var reg 64 X exp_mult_result [63:0] $end
$var reg 32 Y test_a [31:0] $end
$var reg 32 Z test_b [31:0] $end
$var reg 32 [ test_name [31:0] $end
$upscope $end
$upscope $end
$enddefinitions $end
$comment Show the parameter values. $end
$dumpall
b101 O
b100000 N
b100000 I
b100000 C
b101 ;
b100000 :
b101 '
b11111111111111111111111111111111 &
b10000000000000000000000000000000 %
b100000 $
$end
#0
$dumpvars
bx [
bx Z
bx Y
bx X
b0 W
b0 V
b100000101000100010001000011101000100000010011100110111101110010011011010110000101101100 U
b1110111001101011001010000000000 T
b111011100110101100101000000000 S
b10110010110100000101111000000000 R
0Q
b111011100110101100101000000000 P
b0 M
b0 L
b111011100110101100101000000000 K
b110011000100001000000000000000 J
b0 H
b1110111001101011001010000000000 G
b111011100110101100101000000000 F
b10110010110100000101111000000000 E
bx D
b10110010110100000101111000000000 B
b111000100011001010011011000000000 A
b1110111001101011001010000000000 @
b0 ?
b111011100110101100101000000000 >
b10110010110100000101111000000000 =
bx <
09
bx 8
b10110010110100000101111000000000 7
b110011000100001000000000000000 6
b111011100110101100101000000000 5
b0 4
b0 3
b0 2
b0 1
b1110111001101011001010000000000 0
b111011100110101100101000000000 /
b1 .
b0 -
b0 ,
b0 +
b0 *
b1110111001101011001010000000000 )
b111011100110101100101000000000 (
0#
bx "
b10110010110100000101111000000000 !
$end
#10
1#
b0 !
b0 =
19
b0 7
b0 E
b10000000000000000000000000000000 6
b10000000000000000000000000000000 J
b10000000000000000000000000000000 5
b10000000000000000000000000000000 P
b10000000000000000000000000000000 )
b10000000000000000000000000000000 0
b10000000000000000000000000000000 @
b10000000000000000000000000000000 G
b100000000000000000000000000000000 B
b0 A
b10000000000000000000000000000000 (
b10000000000000000000000000000000 /
b10000000000000000000000000000000 >
b10000000000000000000000000000000 F
b10000000000000000000000000000000 K
b10 .
b101000100010001000011101000100000010011110111011001100101011100100110011001101100011011110111011100100000010011010110100101100100 U
1Q
b0 R
b10000000000000000000000000000000 T
b10000000000000000000000000000000 S
b1 -
#20
b1 6
b1 J
b11111111111111111111111111111111 5
b11111111111111111111111111111111 P
b1 )
b1 0
b1 @
b1 G
b100000000000000000000000000000000 B
b11111111111111111111111111111110 A
b11111111111111111111111111111111 (
b11111111111111111111111111111111 /
b11111111111111111111111111111111 >
b11111111111111111111111111111111 F
b11111111111111111111111111111111 K
b11 .
b1000001010001000100010000111010001000000100110101100001011110000010101100110001 U
b1 T
b11111111111111111111111111111111 S
b10 -
#30
b11111111111111111111111111111110 !
b11111111111111111111111111111110 =
b11111111111111111111111111111110 7
b11111111111111111111111111111110 E
b11111111111111111111111111111111 6
b11111111111111111111111111111111 J
b111111111111111111111111111111110 B
b0 A
b11111111111111111111111111111111 )
b11111111111111111111111111111111 0
b11111111111111111111111111111111 @
b11111111111111111111111111111111 G
b100 .
b10000010100010001000100001110100010000001001101011000010111100000101011010011010110000101111000 U
b11111111111111111111111111111110 R
b11111111111111111111111111111111 T
b11 -
#40
b1 M
0#
b1110111001101011001010000000000 !
b1110111001101011001010000000000 =
b1 4
b1 ?
b1 H
09
b1110111001101011001010000000000 7
b1110111001101011001010000000000 E
b10111011110110101101111000000000 6
b10111011110110101101111000000000 J
b10110010110100000101111000000000 5
b10110010110100000101111000000000 P
b1 *
b1 1
b111011100110101100101000000000 )
b111011100110101100101000000000 0
b111011100110101100101000000000 @
b111011100110101100101000000000 G
b11101110011010110010100000000000 B
b1110111001101011001010000000000 A
b10110010110100000101111000000000 (
b10110010110100000101111000000000 /
b10110010110100000101111000000000 >
b10110010110100000101111000000000 F
b10110010110100000101111000000000 K
b101 .
b101001101010101010000100011101000100000010011100110111101110010011011010110000101101100 U
0Q
b1110111001101011001010000000000 R
b1 V
b111011100110101100101000000000 T
b10110010110100000101111000000000 S
b100 -
#50
1#
b11111111111111111101100011110000 !
b11111111111111111101100011110000 =
19
b11111111111111111101100011110000 7
b11111111111111111101100011110000 E
b110111100110000 6
b110111100110000 J
b10011100010000 5
b10011100010000 P
b100111000100000 )
b100111000100000 0
b100111000100000 @
b100111000100000 G
b111010100110000 B
b111111111111111111101100011110000 A
b10011100010000 (
b10011100010000 /
b10011100010000 >
b10011100010000 F
b10011100010000 K
b110 .
b101001101010101010000100011101000100000010101010110111001100100011001010111001001100110011011000110111101110111 U
1Q
b11111111111111111101100011110000 R
b100111000100000 T
b10011100010000 S
b101 -
#60
0#
b11111111111111111111111111111110 !
b11111111111111111111111111111110 =
09
b11111111111111111111111111111110 7
b11111111111111111111111111111110 E
b11111111111111111111111111111111 6
b11111111111111111111111111111111 J
b11111111111111111111111111111111 5
b11111111111111111111111111111111 P
b1 )
b1 0
b1 @
b1 G
b100000000000000000000000000000000 B
b11111111111111111111111111111110 A
b11111111111111111111111111111111 (
b11111111111111111111111111111111 /
b11111111111111111111111111111111 >
b11111111111111111111111111111111 F
b11111111111111111111111111111111 K
b111 .
b1010011010101010100001000111010001000000100110101100001011110000010110100110001 U
0Q
b11111111111111111111111111111110 R
b1 T
b11111111111111111111111111111111 S
b110 -
#70
1#
b11111111111111111111111111111111 !
b11111111111111111111111111111111 =
19
b11111111111111111111111111111111 7
b11111111111111111111111111111111 E
b1 6
b1 J
b0 5
b0 P
b1 B
b111111111111111111111111111111111 A
b0 (
b0 /
b0 >
b0 F
b0 K
b1000 .
b101001101010101010000100011101000100000001100000010110100110001 U
1Q
b11111111111111111111111111111111 R
b0 S
b111 -
#80
b0 !
b0 =
b10 M
b0 7
b0 E
1#
b10 4
b10 ?
b10 H
19
b11111111111111111111111111111111 6
b11111111111111111111111111111111 J
b11111111111111111111111111111111 5
b11111111111111111111111111111111 P
b10 *
b10 1
b0 )
b0 0
b0 @
b0 G
b11111111111111111111111111111111 B
b11111111111111111111111111111111 A
b11111111111111111111111111111111 (
b11111111111111111111111111111111 /
b11111111111111111111111111111111 >
b11111111111111111111111111111111 F
b11111111111111111111111111111111 K
b1001 .
b100100101001110010000110011101000100000010011010110000101111000 U
b0 R
b10 V
b0 T
b11111111111111111111111111111111 S
b1000 -
#90
0#
b111011100110101100101000000001 !
b111011100110101100101000000001 =
09
b111011100110101100101000000001 7
b111011100110101100101000000001 E
b111011100110101100101000000000 6
b111011100110101100101000000000 J
b111011100110101100101000000000 5
b111011100110101100101000000000 P
b111011100110101100101000000000 B
b111011100110101100101000000000 A
b111011100110101100101000000000 (
b111011100110101100101000000000 /
b111011100110101100101000000000 >
b111011100110101100101000000000 F
b111011100110101100101000000000 K
b1010 .
b100100101001110010000110011101000100000010011100110111101110010011011010110000101101100 U
0Q
b111011100110101100101000000001 R
b111011100110101100101000000000 S
b1001 -
#100
1#
b11 M
19
b11111111111111111111111111111111 !
b11111111111111111111111111111111 =
b11 4
b11 ?
b11 H
b11111111111111111111111111111111 7
b11111111111111111111111111111111 E
b11111111111111111111111111111111 6
b11111111111111111111111111111111 J
b0 5
b0 P
b11 *
b11 1
b0 B
b0 A
b0 (
b0 /
b0 >
b0 F
b0 K
b1011 .
b10001000100010101000011001110100010000001011010011001010111001001101111 U
1Q
b11111111111111111111111111111111 R
b11 V
b0 S
b1010 -
#110
0#
b111011100110101100100111111111 !
b111011100110101100100111111111 =
09
b111011100110101100100111111111 7
b111011100110101100100111111111 E
b11000100011001010011010111111111 6
b11000100011001010011010111111111 J
b111011100110101100101000000000 5
b111011100110101100101000000000 P
b111011100110101100101000000000 B
b111011100110101100101000000000 A
b111011100110101100101000000000 (
b111011100110101100101000000000 /
b111011100110101100101000000000 >
b111011100110101100101000000000 F
b111011100110101100101000000000 K
b1100 .
b100010001000101010000110011101000100000010011100110111101110010011011010110000101101100 U
0Q
b111011100110101100100111111111 R
b111011100110101100101000000000 S
b1011 -
#120
b111011100110101100101000000000 "
b111011100110101100101000000000 <
b0 M
b111011100110101100101000000000 8
b111011100110101100101000000000 D
b11000011010011111 !
b11000011010011111 =
b100 4
b100 ?
b100 H
b11000011010011111 7
b11000011010011111 E
b11111111111111111111100111111111 6
b11111111111111111111100111111111 J
b11000011010100000 5
b11000011010100000 P
b100 *
b100 1
b10011100010000 )
b10011100010000 0
b10011100010000 @
b10011100010000 G
b11010110110110000 B
b10101111110010000 A
b11000011010100000 (
b11000011010100000 /
b11000011010100000 >
b11000011010100000 F
b11000011010100000 K
b1101 .
b100000001100010110010100110100 [
b111011100110101100101000000000 X
b10011100010000 Z
b11000011010100000 Y
b1100 -
#130
b10010101000000101111100100000000 "
b10010101000000101111100100000000 <
b10010101000000101111100100000000 8
b10010101000000101111100100000000 D
b11111111111111110011110010101111 6
b11111111111111110011110010101111 J
b1100001101010000 5
b1100001101010000 P
b1100001101010000 )
b1100001101010000 0
b1100001101010000 @
b1100001101010000 G
b11000011010100000 B
b0 A
b1100001101010000 (
b1100001101010000 /
b1100001101010000 >
b1100001101010000 F
b1100001101010000 K
b1110 .
b100000001101010110010100110100 [
b10010101000000101111100100000000 X
b1100001101010000 Z
b1100001101010000 Y
b1101 -
#140
b100000000000000000000000000000000 "
b100000000000000000000000000000000 <
b100000000000000000000000000000000 8
b100000000000000000000000000000000 D
b11111111111111101111111111111111 6
b11111111111111101111111111111111 J
b10000000000000000 5
b10000000000000000 P
b10000000000000000 )
b10000000000000000 0
b10000000000000000 @
b10000000000000000 G
b100000000000000000 B
b0 A
b10000000000000000 (
b10000000000000000 /
b10000000000000000 >
b10000000000000000 F
b10000000000000000 K
b1111 .
b110010010111100011000100110110 [
b100000000000000000000000000000000 X
b10000000000000000 Z
b10000000000000000 Y
b1110 -
#150
b11111111111111111111111111111110 "
b11111111111111111111111111111110 <
b11111111111111111111111111111110 8
b11111111111111111111111111111110 D
b11111111111111111111111111111101 6
b11111111111111111111111111111101 J
b10 5
b10 P
b1111111111111111111111111111111 )
b1111111111111111111111111111111 0
b1111111111111111111111111111111 @
b1111111111111111111111111111111 G
b10000000000000000000000000000001 B
b110000000000000000000000000000011 A
b10 (
b10 /
b10 >
b10 F
b10 K
b10000 .
b1111000001011110011001000101001 [
b11111111111111111111111111111110 X
b1111111111111111111111111111111 Z
b10 Y
b1111 -
