project_4_parametarized_ALU/RTL/shifter_unit.v
module shifter #(
    parameter DATA_WIDTH = 8,
    parameter SHIFT_AMOUNT_WIDTH = $clog2(DATA_WIDTH)
) (
    input signed [DATA_WIDTH-1:0] data,
    input [SHIFT_AMOUNT_WIDTH-1:0] shift_amount,
    input [1:0] shift_op,
    output reg [DATA_WIDTH-1:0] result
);
    always @(*) begin
        case (shift_op)
            2'b00: result = data << shift_amount;  // SLL
            2'b01: result = data >> shift_amount;  // SRL
            2'b10: result = data >>> shift_amount; // SRA
            default: result = data;
        endcase
    end
endmodule

logic_unit.v
module logic_unit #(
    parameter DATA_WIDTH = 8
) (
    input [DATA_WIDTH-1:0] a, b,
    input [2:0] logic_op,
    output  reg [DATA_WIDTH-1:0] result
);
    always @(*) begin
        case (logic_op)
            3'b000: result = a & b;      // AND
            3'b001: result = a | b;      // OR
            3'b010: result = a ^ b;      // XOR
            3'b011: result = ~a;         // NOT
            3'b100: result = ~(a & b);   // NAND
            3'b101: result = ~(a | b);    // NOR
            3'b110 : result = ~(a ^ b);   // XNOR
            default: result = {DATA_WIDTH{1'b0}};
        endcase
    end
endmodule

project_4_parametarized_ALU/RTL/arithmetic_unit.v
module arithmetic_unit #(
    parameter DATA_WIDTH = 8
) (
    input [DATA_WIDTH-1:0] a, b,
    input [2:0] arith_op,
    output reg [DATA_WIDTH-1:0] result,
    output reg carry_out,
    output reg [2*DATA_WIDTH-1:0] mult_result
);

    wire [DATA_WIDTH:0] add_result, sub_result;
    
    // Addition: capture 9-bit result to detect carry
    assign add_result = a + b;
    
    // Subtraction: use two's complement (a - b = a + ~b + 1)
    assign sub_result = a - b;
    
    always @(*) begin
        case (arith_op)
            3'b000: begin
                result = add_result[DATA_WIDTH-1:0];  // 8-bit result
                carry_out = add_result[DATA_WIDTH];    // Carry flag
            end
            3'b001: begin
                result = sub_result[DATA_WIDTH-1:0];
                carry_out = sub_result[DATA_WIDTH];
            end
            3'b010: begin
                result = a + 1;  // INC
                carry_out = (a == {DATA_WIDTH{1'b1}});
            end
            3'b011: begin
                result = a - 1;  // DEC
                carry_out = (a == {DATA_WIDTH{1'b0}});
            end
            3'b100: begin 
                mult_result = a * b; // MUL: 2*data width -bit result
                carry_out=1'b0;
            end
                         
            default: begin
                result = {DATA_WIDTH{1'b0}};
                carry_out = 1'b0;
            end
        endcase
    end
endmodule

project_4_parametarized_ALU/RTL/alu.v
// parameterized ALU Top module

module alu #(
    parameter DATA_WIDTH = 8,
    parameter SHIFT_BITS = $clog2(DATA_WIDTH)
) (
    input [DATA_WIDTH-1:0] a,                    
    input [DATA_WIDTH-1:0] b,                    
    input [4:0] opcode,
    input [SHIFT_BITS-1:0] shift_amount,
    
    output reg [DATA_WIDTH-1:0] result,          
    output reg carry_out,
    output reg [2*DATA_WIDTH-1:0] mult_result
);

    // Internal signals
    wire [DATA_WIDTH-1:0] arith_result;
    wire arith_carry;
    wire [2*DATA_WIDTH-1:0] arith_mult_result;
    
    wire [DATA_WIDTH-1:0] logic_result;
    
    wire [DATA_WIDTH-1:0] shift_result;
    
    wire [1:0] unit_select = opcode[4:3];
    wire [2:0] unit_opcode = opcode[2:0];
    
    //ARITHEMATIC UNIT
    
    arithmetic_unit #(.DATA_WIDTH(DATA_WIDTH)) arith_inst (
        .a(a),
        .b(b),
        .arith_op(unit_opcode),
        .result(arith_result),
        .carry_out(arith_carry),
        .mult_result(arith_mult_result)
    );
    
    // LOGIC UNIT 

    logic_unit #(.DATA_WIDTH(DATA_WIDTH)) logic_inst (
        .a(a),
        .b(b),
        .logic_op(unit_opcode),
        .result(logic_result)
    );
       
    // SHIFTER UNIT 

    shifter #(
        .DATA_WIDTH(DATA_WIDTH),
        .SHIFT_AMOUNT_WIDTH(SHIFT_BITS)
    ) shifter_inst (
        .data(a),              // Passed only the first operand 'a' for shifting
        .shift_amount(shift_amount),
        .shift_op(unit_opcode[1:0]),
        .result(shift_result)
    );
    
    // ============================================================
    // MULTIPLEXER: SELECT OUTPUT BASED ON UNIT
    // ============================================================
    
    always @(*) begin
        case (unit_select)
            2'b00: begin  // ARITHMETIC UNIT
                result = arith_result;
                carry_out = arith_carry;
                mult_result = arith_mult_result;
            end
            
            2'b01: begin  // LOGIC UNIT
                result = logic_result;
                carry_out = 1'b0;
                mult_result = {2*DATA_WIDTH{1'b0}};
            end
            
            2'b10: begin  // SHIFTER UNIT
                result = shift_result;
                carry_out = 1'b0;
                mult_result = {2*DATA_WIDTH{1'b0}};
            end
            
            2'b11: begin  // RESERVED
                result = {DATA_WIDTH{1'b0}};
                carry_out = 1'b0;
                mult_result = {2*DATA_WIDTH{1'b0}};
            end
            default: begin
                result = {DATA_WIDTH{1'b0}};
                carry_out = 1'b0;
                mult_result = {2*DATA_WIDTH{1'b0}};
            end
        endcase
    end
    
endmodule

project_4_parametarized_ALU/tb_alu.v
module tb_alu;
    parameter DATA_WIDTH = 32;
    parameter SHIFT_BITS = $clog2(DATA_WIDTH); // $clog2(32) = 5
    
    reg [DATA_WIDTH-1:0] a, b;
    reg [4:0] opcode;
    reg [SHIFT_BITS-1:0] shift_amount;
    wire [DATA_WIDTH-1:0] result;
    wire carry_out;
    wire [2*DATA_WIDTH-1:0] mult_result; // 64 bits

    // Max 32-bit value
    localparam MAX_32 = 32'hFFFF_FFFF; // 4294967295
    localparam HALF_32 = 32'h8000_0000; // 2147483648
    
    // Instantiate ALU
    alu #(.DATA_WIDTH(DATA_WIDTH), .SHIFT_BITS(SHIFT_BITS)) uut (
        .a(a), .b(b), .opcode(opcode), .shift_amount(shift_amount),
        .result(result), .carry_out(carry_out), .mult_result(mult_result)
    );
    
    integer test_count = 0;
    integer pass_count = 0;
    integer fail_count = 0;
    
    // Task for regular operations (ADD, SUB, INC, DEC, AND, OR, XOR, etc.)
    task run_test;
        input [DATA_WIDTH-1:0] test_a;
        input [DATA_WIDTH-1:0] test_b;
        input [4:0] test_opcode;
        input [SHIFT_BITS-1:0] test_shift;
        input [DATA_WIDTH-1:0] exp_result;
        input exp_carry;
        input [132:0] test_name;
        
        begin
            test_count = test_count + 1;
            a = test_a;
            b = test_b;
            opcode = test_opcode;
            shift_amount = test_shift;
            #10;
            
            if (result == exp_result && carry_out == exp_carry) begin
                $display("[PASS %3d] %-20s | a=%10d, b=%10d, shift=%d | result=%10d, carry=%b", 
                         test_count, test_name, test_a, test_b, test_shift, result, carry_out);
                pass_count = pass_count + 1;
            end else begin
                $display("[FAIL %3d] %-20s | a=%10d, b=%10d, shift=%d | Got: result=%10d, carry=%b | Exp: result=%10d, carry=%b", 
                         test_count, test_name, test_a, test_b, test_shift, result, carry_out, exp_result, exp_carry);
                fail_count = fail_count + 1;
            end
        end
    endtask
    
    // Task for MUL operations (verifies mult_result output)
    task run_test_mul;
        input [DATA_WIDTH-1:0] test_a;
        input [DATA_WIDTH-1:0] test_b;
        input [2*DATA_WIDTH-1:0] exp_mult_result;
        input [31:0] test_name;
        
        begin
            test_count = test_count + 1;
            a = test_a;
            b = test_b;
            opcode = 5'b00_100;  // MUL opcode
            shift_amount = 5'b00000;
            #10;
            
            if (mult_result == exp_mult_result) begin
                $display("[PASS %3d] %-20s | a=%10d, b=%10d | mult_result=%20d", 
                         test_count, test_name, test_a, test_b, mult_result);
                pass_count = pass_count + 1;
            end else begin
                $display("[FAIL %3d] %-20s | a=%10d, b=%10d | Got mult_result=%20d | Expected: %20d", 
                         test_count, test_name, test_a, test_b, mult_result, exp_mult_result);
                fail_count = fail_count + 1;
            end
        end
    endtask
    
    initial begin
        $display("\n");
        $display("╔══════════════════════════════════════════════════════════════════════╗");
        $display("║       COMPREHENSIVE ALU TEST SUITE (DATA_WIDTH = %d bits)            ║", DATA_WIDTH);
        $display("╚══════════════════════════════════════════════════════════════════════╝\n");
        
        
        // ================================================================
        // ARITHMETIC UNIT TESTS (opcode[4:3] = 2'b00)
        // ================================================================
        
        $display("═══════════════════════════════════════════════════════════════════════");
        $display("ARITHMETIC UNIT TESTS (Opcode 5'b00_XXX)");
        $display("═══════════════════════════════════════════════════════════════════════\n");
        
        // ─────────────────────────────────────────────────────────────
        // ADD Tests (opcode = 5'b00_000)
        // ─────────────────────────────────────────────────────────────
        $display("--- ADD OPERATION (5'b00_000) ---");
        run_test(32'd1000000000, 32'd2000000000, 5'b00_000, 5'b00000, 32'd3000000000, 1'b0, "ADD: Normal");
        run_test(HALF_32,        HALF_32,        5'b00_000, 5'b00000, 32'd0,          1'b1, "ADD: Overflow Mid");
        run_test(MAX_32,         32'd1,          5'b00_000, 5'b00000, 32'd0,          1'b1, "ADD: Max+1");
        run_test(MAX_32,         MAX_32,         5'b00_000, 5'b00000, 32'd4294967294, 1'b1, "ADD: Max+Max");
        
        // ─────────────────────────────────────────────────────────────
        // SUB Tests (opcode = 5'b00_001)
        // ─────────────────────────────────────────────────────────────
        $display("\n--- SUB OPERATION (5'b00_001) ---");
        run_test(32'd3000000000, 32'd1000000000, 5'b00_001, 5'b00000, 32'd2000000000, 1'b0, "SUB: Normal");
        run_test(32'd10000,      32'd20000,      5'b00_001, 5'b00000, 32'd4294957296, 1'b1, "SUB: Underflow");
        run_test(MAX_32,         32'd1,          5'b00_001, 5'b00000, 32'd4294967294, 1'b0, "SUB: Max-1");
        run_test(32'd0,          32'd1,          5'b00_001, 5'b00000, MAX_32,         1'b1, "SUB: 0-1");
        
        // ─────────────────────────────────────────────────────────────
        // INC Tests (opcode = 5'b00_010)
        // ─────────────────────────────────────────────────────────────
        $display("\n--- INC OPERATION (5'b00_010) ---");
        run_test(MAX_32, 32'd0, 5'b00_010, 5'b00000, 32'd0,            1'b1, "INC: Max");
        run_test(32'd1000000000, 32'd0, 5'b00_010, 5'b00000, 32'd1000000001, 1'b0, "INC: Normal");
        
        // ─────────────────────────────────────────────────────────────
        // DEC Tests (opcode = 5'b00_011)
        // ─────────────────────────────────────────────────────────────
        $display("\n--- DEC OPERATION (5'b00_011) ---");
        run_test(32'd0, 32'd0, 5'b00_011, 5'b00000, MAX_32,         1'b1, "DEC: Zero");
        run_test(32'd1000000000, 32'd0, 5'b00_011, 5'b00000, 32'd999999999, 1'b0, "DEC: Normal");
        
        // ─────────────────────────────────────────────────────────────
        // MUL Tests (opcode = 5'b00_100) - USING MUL TASK
        // ─────────────────────────────────────────────────────────────
        $display("\n--- MUL OPERATION (5'b00_100) ---");
        run_test_mul(32'd100000, 32'd10000, 64'd1000000000,          "MUL: 1e5 * 1e4");
        run_test_mul(32'd50000, 32'd50000, 64'd2500000000,           "MUL: 5e4 * 5e4");
        run_test_mul(32'd65536, 32'd65536, 64'd4294967296,           "MUL: 2^16 * 2^16");
        run_test_mul(32'd2,     32'd2147483647, 64'd4294967294,      "MUL: 2 * (Max/2)");
        
        // ================================================================
        // LOGIC UNIT TESTS (opcode[4:3] = 2'b01)
        // ================================================================
        
        $display("\n═══════════════════════════════════════════════════════════════════════");
        $display("LOGIC UNIT TESTS (Opcode 5'b01_XXX)");
        $display("═══════════════════════════════════════════════════════════════════════\n");
        
        // ─────────────────────────────────────────────────────────────
        // AND Tests (opcode = 5'b01_000)
        // ─────────────────────────────────────────────────────────────
        $display("--- AND OPERATION (5'b01_000) ---");
        run_test(32'hFFFF0000, 32'h0000FFFF, 5'b01_000, 5'b00000, 32'h00000000, 1'b0, "AND: Disjoint");
        run_test(32'hAAAA_AAAA, 32'h5555_5555, 5'b01_000, 5'b00000, 32'h0000_0000, 1'b0, "AND: Complement");
        
        // ─────────────────────────────────────────────────────────────
        // OR Tests (opcode = 5'b01_001)
        // ─────────────────────────────────────────────────────────────
        $display("\n--- OR OPERATION (5'b01_001) ---");
        run_test(32'hFFFF0000, 32'h0000FFFF, 5'b01_001, 5'b00000, 32'hFFFFFFFF, 1'b0, "OR: Combine");
        
        // ─────────────────────────────────────────────────────────────
        // XOR Tests (opcode = 5'b01_010)
        // ─────────────────────────────────────────────────────────────
        $display("\n--- XOR OPERATION (5'b01_010) ---");
        run_test(32'hFFFF0000, 32'hFFFF0000, 5'b01_010, 5'b00000, 32'h00000000, 1'b0, "XOR: Same");
        
        // ─────────────────────────────────────────────────────────────
        // NOT Tests (opcode = 5'b01_011)
        // ─────────────────────────────────────────────────────────────
        $display("\n--- NOT OPERATION (5'b01_011) ---");
        run_test(32'hF0F0F0F0, 32'd0, 5'b01_011, 5'b00000, 32'h0F0F0F0F, 1'b0, "NOT: Pattern");
        
        // ─────────────────────────────────────────────────────────────
        // NAND Tests (opcode = 5'b01_100)
        // ─────────────────────────────────────────────────────────────
        $display("\n--- NAND OPERATION (5'b01_100) ---");
        run_test(32'hFFFF0000, 32'h0000FFFF, 5'b01_100, 5'b00000, 32'hFFFFFFFF, 1'b0, "NAND: Disjoint");
        
        // ─────────────────────────────────────────────────────────────
        // NOR Tests (opcode = 5'b01_101)
        // ─────────────────────────────────────────────────────────────
        $display("\n--- NOR OPERATION (5'b01_101) ---");
        run_test(32'hFFFF0000, 32'h0000FFFF, 5'b01_101, 5'b00000, 32'h00000000, 1'b0, "NOR: Combine");
        
        // ─────────────────────────────────────────────────────────────
        // XNOR Tests (opcode = 5'b01_110)
        // ─────────────────────────────────────────────────────────────
        $display("\n--- XNOR OPERATION (5'b01_110) ---");
        run_test(32'hAAAA_AAAA, 32'h5555_5555, 5'b01_110, 5'b00000, 32'h0000_0000, 1'b0, "XNOR: Complement");
        
        // ================================================================
        // SHIFTER UNIT TESTS (opcode[4:3] = 2'b10)
        // ================================================================
        
        $display("\n═══════════════════════════════════════════════════════════════════════");
        $display("SHIFTER UNIT TESTS (Opcode 5'b10_XXX)");
        $display("═══════════════════════════════════════════════════════════════════════\n");
        
        // ─────────────────────────────────────────────────────────────
        // SLL Tests (opcode = 5'b10_000, shift_op = 2'b00)
        // ─────────────────────────────────────────────────────────────
        $display("--- SLL OPERATION (5'b10_000) - Shift Left Logical ---");
        run_test(32'h00000001, 32'd0, 5'b10_000, 5'd31, 32'h80000000, 1'b0, "SLL: Shift 31");
        run_test(32'h80000000, 32'd0, 5'b10_000, 5'd1, 32'h00000000, 1'b0, "SLL: MSB Out");
        
        // ─────────────────────────────────────────────────────────────
        // SRL Tests (opcode = 5'b10_001, shift_op = 2'b01)
        // ─────────────────────────────────────────────────────────────
        $display("\n--- SRL OPERATION (5'b10_001) - Shift Right Logical ---");
        run_test(32'h80000000, 32'd0, 5'b10_001, 5'd1, 32'h40000000, 1'b0, "SRL: Normal 1");
        run_test(32'h80000000, 32'd0, 5'b10_001, 5'd31, 32'h00000001, 1'b0, "SRL: Shift 31");
        
        // ─────────────────────────────────────────────────────────────
        // SRA Tests (opcode = 5'b10_010, shift_op = 2'b10)
        // ─────────────────────────────────────────────────────────────
        $display("\n--- SRA OPERATION (5'b10_010) - Shift Right Arithmetic ---");
        run_test(32'h80000000, 32'd0, 5'b10_010, 5'd1, 32'hC0000000, 1'b0, "SRA: Max neg >> 1"); // -2^31 >> 1 = -2^30
        run_test(32'hF0000000, 32'd0, 5'b10_010, 5'd4, 32'hFF000000, 1'b0, "SRA: Negative 4");
        run_test(32'h80000000, 32'd0, 5'b10_010, 5'd31, 32'hFFFFFFFF, 1'b0, "SRA: Neg to -1");
        
        // ================================================================
        // FLAG VERIFICATION TESTS
        // ================================================================
        
        $display("\n═══════════════════════════════════════════════════════════════════════");
        $display("FLAG VERIFICATION TESTS");
        $display("═══════════════════════════════════════════════════════════════════════\n");
        
        $display("--- Carry Flag Tests ---");
        run_test(MAX_32, 32'd1,  5'b00_000, 5'b00000, 32'd0,     1'b1, "Carry from ADD");
        run_test(32'd0,  32'd1,  5'b00_011, 5'b00000, MAX_32,    1'b1, "Carry from DEC (Borrow)");
        
        $display("\n--- No Carry Tests (Logic, Shifter) ---");
        run_test(32'hFFFFFFFF, 32'd0, 5'b01_011, 5'b00000, 32'h00000000, 1'b0, "Logic: No carry");
        run_test(32'hAAAA_AAAA, 32'd0, 5'b10_000, 5'd10, 32'hAAAAA800, 1'b0, "Shifter: No carry");
        
        // ================================================================
        // TEST SUMMARY
        // ================================================================
        
        $display("\n═══════════════════════════════════════════════════════════════════════");
        $display("╔══════════════════════════════════════════════════════════════════════╗");
        $display("║                           TEST SUMMARY                               ║");
        $display("╠══════════════════════════════════════════════════════════════════════╣");
        $display("║ Total Tests:       %3d                                               ║", test_count);
        $display("║ Passed:            %3d                                               ║", pass_count);
        $display("║ Failed:            %3d                                               ║", fail_count);
        if (test_count > 0)
            $display("║ Success Rate:      %6.2f%%                                            ║", (pass_count * 100.0) / test_count);
        $display("╚══════════════════════════════════════════════════════════════════════╝\n");
        
        if (fail_count == 0) begin
            $display("✓ ALL TESTS PASSED - ALU DESIGN VERIFIED!");
        end else begin
            $display("✗ %d TESTS FAILED - REVIEW DESIGN", fail_count);
        end
        
        $display("\n");
        $finish;
    end
    
endmodule

project_4_parametarized_ALU/sim_wave/tb_alu_8.vcd
$date
	Thu Nov 27 11:11:24 2025
$end
$version
	Icarus Verilog
$end
$timescale
	1s
$end
$scope module tb_alu $end
$var wire 8 ! result [7:0] $end
$var wire 16 " mult_result [15:0] $end
$var wire 1 # carry_out $end
$var parameter 32 $ DATA_WIDTH $end
$var parameter 32 % SHIFT_BITS $end
$var reg 8 & a [7:0] $end
$var reg 8 ' b [7:0] $end
$var reg 5 ( opcode [4:0] $end
$var reg 3 ) shift_amount [2:0] $end
$var integer 32 * fail_count [31:0] $end
$var integer 32 + pass_count [31:0] $end
$var integer 32 , test_count [31:0] $end
$scope module uut $end
$var wire 8 - a [7:0] $end
$var wire 8 . b [7:0] $end
$var wire 5 / opcode [4:0] $end
$var wire 3 0 shift_amount [2:0] $end
$var wire 2 1 unit_select [1:0] $end
$var wire 3 2 unit_opcode [2:0] $end
$var wire 8 3 shift_result [7:0] $end
$var wire 8 4 logic_result [7:0] $end
$var wire 8 5 arith_result [7:0] $end
$var wire 16 6 arith_mult_result [15:0] $end
$var wire 1 7 arith_carry $end
$var parameter 32 8 DATA_WIDTH $end
$var parameter 32 9 SHIFT_BITS $end
$var reg 1 # carry_out $end
$var reg 16 : mult_result [15:0] $end
$var reg 8 ; result [7:0] $end
$scope module arith_inst $end
$var wire 8 < a [7:0] $end
$var wire 3 = arith_op [2:0] $end
$var wire 8 > b [7:0] $end
$var wire 9 ? sub_result [8:0] $end
$var wire 9 @ add_result [8:0] $end
$var parameter 32 A DATA_WIDTH $end
$var reg 1 7 carry_out $end
$var reg 16 B mult_result [15:0] $end
$var reg 8 C result [7:0] $end
$upscope $end
$scope module logic_inst $end
$var wire 8 D a [7:0] $end
$var wire 8 E b [7:0] $end
$var wire 3 F logic_op [2:0] $end
$var parameter 32 G DATA_WIDTH $end
$var reg 8 H result [7:0] $end
$upscope $end
$scope module shifter_inst $end
$var wire 8 I data [7:0] $end
$var wire 3 J shift_amount [2:0] $end
$var wire 2 K shift_op [1:0] $end
$var parameter 32 L DATA_WIDTH $end
$var parameter 32 M SHIFT_AMOUNT_WIDTH $end
$var reg 8 N result [7:0] $end
$upscope $end
$upscope $end
$scope task run_test $end
$var reg 1 O exp_carry $end
$var reg 8 P exp_result [7:0] $end
$var reg 8 Q test_a [7:0] $end
$var reg 8 R test_b [7:0] $end
$var reg 133 S test_name [132:0] $end
$var reg 5 T test_opcode [4:0] $end
$var reg 3 U test_shift [2:0] $end
$upscope $end
$scope task run_test_mul $end
$var reg 16 V exp_mult_result [15:0] $end
$var reg 8 W test_a [7:0] $end
$var reg 8 X test_b [7:0] $end
$var reg 32 Y test_name [31:0] $end
$upscope $end
$upscope $end
$enddefinitions $end
$comment Show the parameter values. $end
$dumpall
b11 M
b1000 L
b1000 G
b1000 A
b11 9
b1000 8
b11 %
b1000 $
$end
#0
$dumpvars
bx Y
bx X
bx W
bx V
b0 U
b0 T
b100000101000100010001000011101000100000010011100110111101110010011011010110000101101100 S
b1100100 R
b10010110 Q
b11111010 P
0O
b10010110 N
b0 K
b0 J
b10010110 I
b100 H
b0 F
b1100100 E
b10010110 D
b11111010 C
bx B
b11111010 @
b110010 ?
b1100100 >
b0 =
b10010110 <
b11111010 ;
bx :
07
bx 6
b11111010 5
b100 4
b10010110 3
b0 2
b0 1
b0 0
b0 /
b1100100 .
b10010110 -
b1 ,
b0 +
b0 *
b0 )
b0 (
b1100100 '
b10010110 &
0#
bx "
b11111010 !
$end
#10
1#
b101100 !
b101100 ;
17
b101100 5
b101100 C
b1000000 4
b1000000 H
b11001000 3
b11001000 N
b100101100 @
b1100100 ?
b11001000 &
b11001000 -
b11001000 <
b11001000 D
b11001000 I
b10 ,
b1000001010001000100010000111010001000000100111101110110011001010111001001100110011011000110111101110111 S
1O
b101100 P
b11001000 Q
b1 +
#20
b0 !
b0 ;
b0 5
b0 C
b1 4
b1 H
b11111111 3
b11111111 N
b1 '
b1 .
b1 >
b1 E
b100000000 @
b11111110 ?
b11111111 &
b11111111 -
b11111111 <
b11111111 D
b11111111 I
b11 ,
b1000001010001000100010000111010001000000100110101100001011110000010101100110001 S
b0 P
b1 R
b11111111 Q
b10 +
#30
0#
07
b0 4
b0 H
b0 3
b0 N
b0 '
b0 .
b0 >
b0 E
b0 @
b0 ?
b0 &
b0 -
b0 <
b0 D
b0 I
b100 ,
b100000101000100010001000011101000100000010110100110010101110010011011110010101101011010011001010111001001101111 S
0O
b0 R
b0 Q
b11 +
#40
b11111111 !
b11111111 ;
b11111111 5
b11111111 C
b10000000 3
b10000000 N
b1111111 '
b1111111 .
b1111111 >
b1111111 E
b11111111 @
b1 ?
b10000000 &
b10000000 -
b10000000 <
b10000000 D
b10000000 I
b101 ,
b1000001010001000100010000111010001000000100111001100101011000010111001000100000010011010110000101111000 S
b11111111 P
b1111111 R
b10000000 Q
b100 +
#50
1#
b11111110 !
b11111110 ;
17
b11111110 5
b11111110 C
b11111111 4
b11111111 H
b11111111 3
b11111111 N
b11111111 '
b11111111 .
b11111111 >
b11111111 E
b111111110 @
b0 ?
b11111111 &
b11111111 -
b11111111 <
b11111111 D
b11111111 I
b110 ,
b10000010100010001000100001110100010000001001101011000010111100000101011010011010110000101111000 S
1O
b11111110 P
b11111111 R
b11111111 Q
b101 +
#60
0#
b10 !
b10 ;
07
b10 5
b10 C
b1 4
b1 H
b1 3
b1 N
b1 '
b1 .
b1 >
b1 E
b10 @
b0 ?
b1 &
b1 -
b1 <
b1 D
b1 I
b111 ,
b10000010100010001000100001110100010000001001111011011100110010100101011010011110110111001100101 S
0O
b10 P
b1 R
b1 Q
b110 +
#70
b10000000 !
b10000000 ;
b10000000 5
b10000000 C
b1111111 3
b1111111 N
b10000000 @
b1111110 ?
b1111111 &
b1111111 -
b1111111 <
b1111111 D
b1111111 I
b1000 ,
b1000001010001000100010000111010001000000100001001101111011101010110111001100100011000010111001001111001 S
b10000000 P
b1111111 Q
b111 +
#80
b1 K
b110010 !
b110010 ;
b1 2
b1 =
b1 F
b110010 5
b110010 C
b11110110 4
b11110110 H
b10010110 3
b10010110 N
b1 (
b1 /
b1100100 '
b1100100 .
b1100100 >
b1100100 E
b11111010 @
b110010 ?
b10010110 &
b10010110 -
b10010110 <
b10010110 D
b10010110 I
b1001 ,
b101001101010101010000100011101000100000010011100110111101110010011011010110000101101100 S
b110010 P
b1 T
b1100100 R
b10010110 Q
b1000 +
#90
1#
b11001110 !
b11001110 ;
17
b11001110 5
b11001110 C
b1110110 4
b1110110 H
b110010 3
b110010 N
b10010110 @
b111001110 ?
b110010 &
b110010 -
b110010 <
b110010 D
b110010 I
b1010 ,
b101001101010101010000100011101000100000010101010110111001100100011001010111001001100110011011000110111101110111 S
1O
b11001110 P
b110010 Q
b1001 +
#100
0#
b11111110 !
b11111110 ;
07
b11111110 5
b11111110 C
b11111111 4
b11111111 H
b11111111 3
b11111111 N
b1 '
b1 .
b1 >
b1 E
b100000000 @
b11111110 ?
b11111111 &
b11111111 -
b11111111 <
b11111111 D
b11111111 I
b1011 ,
b1010011010101010100001000111010001000000100110101100001011110000010110100110001 S
0O
b11111110 P
b1 R
b11111111 Q
b1010 +
#110
b0 !
b0 ;
b0 5
b0 C
b0 4
b0 H
b0 3
b0 N
b0 '
b0 .
b0 >
b0 E
b0 @
b0 ?
b0 &
b0 -
b0 <
b0 D
b0 I
b1100 ,
b101001101010101010000100011101000100000010110100110010101110010011011110010110101011010011001010111001001101111 S
b0 P
b0 R
b0 Q
b1011 +
#120
b1100100 4
b1100100 H
b1100100 3
b1100100 N
b1100100 '
b1100100 .
b1100100 >
b1100100 E
b11001000 @
b0 ?
b1100100 &
b1100100 -
b1100100 <
b1100100 D
b1100100 I
b1101 ,
b1010011010101010100001000111010001000000100010101110001011101010110000101101100 S
b1100100 R
b1100100 Q
b1100 +
#130
1#
b11111111 !
b11111111 ;
17
b11111111 5
b11111111 C
b1 4
b1 H
b0 3
b0 N
b1 '
b1 .
b1 >
b1 E
b1 @
b111111111 ?
b0 &
b0 -
b0 <
b0 D
b0 I
b1110 ,
b101001101010101010000100011101000100000001100000010110100110001 S
1O
b11111111 P
b1 R
b0 Q
b1101 +
#140
0#
b0 !
b0 ;
07
b0 5
b0 C
b10000000 4
b10000000 H
b10000000 3
b10000000 N
b10000000 '
b10000000 .
b10000000 >
b10000000 E
b100000000 @
b0 ?
b10000000 &
b10000000 -
b10000000 <
b10000000 D
b10000000 I
b1111 ,
b10100110101010101000010001110100010000001001101011010010110010000101101010011010110100101100100 S
0O
b0 P
b10000000 R
b10000000 Q
b1110 +
#150
b10010110 !
b10010110 ;
b10010110 5
b10010110 C
b11111010 4
b11111010 H
b11001000 3
b11001000 N
b110010 '
b110010 .
b110010 >
b110010 E
b11111010 @
b10010110 ?
b11001000 &
b11001000 -
b11001000 <
b11001000 D
b11001000 I
b10000 ,
b1010011010101010100001000111010001000000100110001100001011100100110011101100101001011010101001101101101011000010110110001101100 S
b10010110 P
b110010 R
b11001000 Q
b1111 +
#160
1#
b10 K
17
b0 !
b0 ;
b10 2
b10 =
b10 F
b0 5
b0 C
b11111111 4
b11111111 H
b11111111 3
b11111111 N
b10 (
b10 /
b0 '
b0 .
b0 >
b0 E
b11111111 @
b11111111 ?
b11111111 &
b11111111 -
b11111111 <
b11111111 D
b11111111 I
b10001 ,
b100100101001110010000110011101000100000010011010110000101111000 S
1O
b0 P
b10 T
b0 R
b11111111 Q
b10000 +
#170
0#
b1100101 !
b1100101 ;
07
b1100101 5
b1100101 C
b1100100 4
b1100100 H
b1100100 3
b1100100 N
b1100100 @
b1100100 ?
b1100100 &
b1100100 -
b1100100 <
b1100100 D
b1100100 I
b10010 ,
b100100101001110010000110011101000100000010011100110111101110010011011010110000101101100 S
0O
b1100101 P
b1100100 Q
b10001 +
#180
b1 !
b1 ;
b1 5
b1 C
b0 4
b0 H
b0 3
b0 N
b0 @
b0 ?
b0 &
b0 -
b0 <
b0 D
b0 I
b10011 ,
b10010010100111001000011001110100010000001011010011001010111001001101111 S
b1 P
b0 Q
b10010 +
#190
b10000000 !
b10000000 ;
b10000000 5
b10000000 C
b1111111 4
b1111111 H
b1111111 3
b1111111 N
b1111111 @
b1111111 ?
b1111111 &
b1111111 -
b1111111 <
b1111111 D
b1111111 I
b10100 ,
b100100101001110010000110011101000100000010011010110100101100100 S
b10000000 P
b1111111 Q
b10011 +
#200
b11111111 !
b11111111 ;
b11111111 5
b11111111 C
b11111110 4
b11111110 H
b11111110 3
b11111110 N
b11111110 @
b11111110 ?
b11111110 &
b11111110 -
b11111110 <
b11111110 D
b11111110 I
b10101 ,
b1001001010011100100001100111010001000000100111001100101011000010111001000100000010011010110000101111000 S
b11111111 P
b11111110 Q
b10100 +
#210
b10 !
b10 ;
b10 5
b10 C
b1 4
b1 H
b1 3
b1 N
b1 @
b1 ?
b1 &
b1 -
b1 <
b1 D
b1 I
b10110 ,
b100100101001110010000110011101000100000010011110110111001100101 S
b10 P
b1 Q
b10101 +
#220
1#
b11 K
17
b11111111 !
b11111111 ;
b11 2
b11 =
b11 F
b11111111 5
b11111111 C
b11111111 4
b11111111 H
b0 3
b0 N
b11 (
b11 /
b0 @
b0 ?
b0 &
b0 -
b0 <
b0 D
b0 I
b10111 ,
b10001000100010101000011001110100010000001011010011001010111001001101111 S
1O
b11111111 P
b11 T
b0 Q
b10110 +
#230
0#
b1100011 !
b1100011 ;
07
b1100011 5
b1100011 C
b10011011 4
b10011011 H
b1100100 3
b1100100 N
b1100100 @
b1100100 ?
b1100100 &
b1100100 -
b1100100 <
b1100100 D
b1100100 I
b11000 ,
b100010001000101010000110011101000100000010011100110111101110010011011010110000101101100 S
0O
b1100011 P
b1100100 Q
b10111 +
#240
b0 !
b0 ;
b0 5
b0 C
b11111110 4
b11111110 H
b1 3
b1 N
b1 @
b1 ?
b1 &
b1 -
b1 <
b1 D
b1 I
b11001 ,
b100010001000101010000110011101000100000010011110110111001100101 S
b0 P
b1 Q
b11000 +
#250
b1111111 !
b1111111 ;
b1111111 5
b1111111 C
b1111111 4
b1111111 H
b10000000 3
b10000000 N
b10000000 @
b10000000 ?
b10000000 &
b10000000 -
b10000000 <
b10000000 D
b10000000 I
b11010 ,
b100010001000101010000110011101000100000010011010110100101100100 S
b1111111 P
b10000000 Q
b11001 +
#260
b11111110 !
b11111110 ;
b11111110 5
b11111110 C
b0 4
b0 H
b11111111 3
b11111111 N
b11111111 @
b11111111 ?
b11111111 &
b11111111 -
b11111111 <
b11111111 D
b11111111 I
b11011 ,
b100010001000101010000110011101000100000010011010110000101111000 S
b11111110 P
b11111111 Q
b11010 +
