enum_adv/enum_alu.sv
package alu_pkg;
    typedef enum {add,sub,and_op,or_op,not_op,xor_op,right_shift,left_shift,right_sign_shift} alu_state;

    
endpackage

module enum_alu
import alu_pkg::*;
#(parameter WIDTH = 8)
(
    input logic [WIDTH-1:0] in_a,in_b,
    input alu_state op_code,
    input logic [$clog2(WIDTH)-1:0] shift_amt,
    output logic [WIDTH-1:0] out
);

always_comb begin

    out = '0; // Default assignment

    case(op_code)

        add : out = in_a + in_b;
        sub : out = in_a - in_b;
        and_op : out = in_a & in_b;
        or_op : out = in_a | in_b;
        not_op : out = ~in_a;
        xor_op : out = in_a ^ in_b;
        right_shift : out = in_a >> shift_amt;
        left_shift : out = in_a << shift_amt;
        right_sign_shift : out = $signed(in_a) >>> shift_amt;
        default : out = 'x;

    
    endcase



end


endmodule

enum_adv/tb_enum_alu.sv
module tb_enum_alu;
    import alu_pkg::*;

    parameter WIDTH = 8;
    logic [WIDTH-1:0] in_a, in_b;
    alu_state op_code;
    logic [$clog2(WIDTH)-1:0] shift_amt;
    logic [WIDTH-1:0] out;

    // Instantiate with name "u_dut"
    enum_alu #(WIDTH) u_dut (.*);  // a auto connection way to connect ports and signals of design and tb with same names.  

    always @(in_a, in_b, op_code, shift_amt, out) begin
        #0;
        $display("Time: %0t | in_a: %0d | in_b: %0d | op: %s | shift: %0d | out: %0d", 
                 $time, 
                 in_a, 
                 in_b, 
                 op_code.name(), // This works in $display!
                 shift_amt, 
                 out
        );
    end

    initial begin
        
        // Test Stimulus
        in_a = 8'd15; in_b = 8'd3; shift_amt = 3'd2;

        op_code = add;          #10;
        op_code = sub;          #10;
        op_code = and_op;       #10;
        op_code = or_op;        #10;
        op_code = not_op;       #10;
        op_code = xor_op;       #10;
        op_code = right_shift;  #10;
        op_code = left_shift;   #10;
        op_code = right_sign_shift; #10;

        in_a = -8'd32;          #10;
        op_code = right_sign_shift; #10;

        in_a = 8'd100; in_b = 8'd25; shift_amt = 3'd3; #10;
        op_code = add;          #10;
        op_code = sub;          #10;
        op_code = and_op;       #10;
        op_code = or_op;        #10;
        op_code = not_op;       #10;
        op_code = xor_op;       #10;
        op_code = right_shift;  #10;
        op_code = left_shift;   #10;
        op_code = right_sign_shift; #10;

        #100 $finish;
    end 

    initial begin
        $dumpfile("out_enum_alu.vcd");
        $dumpvars(0,tb_enum_alu);
    end
    


endmodule

enum_adv/out_enum_alu.vcd
$date
	Fri Jan  2 11:53:48 2026
$end
$version
	Icarus Verilog
$end
$timescale
	1s
$end
$scope module tb_enum_alu $end
$var wire 8 ! out [7:0] $end
$var parameter 32 " WIDTH $end
$var reg 8 # in_a [7:0] $end
$var reg 8 $ in_b [7:0] $end
$var reg 3 % shift_amt [2:0] $end
$var integer 32 & op_code [31:0] $end
$scope module u_dut $end
$var wire 8 ' in_a [7:0] $end
$var wire 8 ( in_b [7:0] $end
$var wire 32 ) op_code [31:0] $end
$var wire 3 * shift_amt [2:0] $end
$var parameter 32 + WIDTH $end
$var reg 8 , out [7:0] $end
$upscope $end
$upscope $end
$enddefinitions $end
$comment Show the parameter values. $end
$dumpall
b1000 +
b1000 "
$end
#0
$dumpvars
b10010 ,
b10 *
b0 )
b11 (
b1111 '
b0 &
b10 %
b11 $
b1111 #
b10010 !
$end
#10
b1100 !
b1100 ,
b1 &
b1 )
#20
b11 !
b11 ,
b10 &
b10 )
#30
b1111 !
b1111 ,
b11 &
b11 )
#40
b11110000 !
b11110000 ,
b100 &
b100 )
#50
b1100 !
b1100 ,
b101 &
b101 )
#60
b11 !
b11 ,
b110 &
b110 )
#70
b111100 !
b111100 ,
b111 &
b111 )
#80
b11 !
b11 ,
b1000 &
b1000 )
#90
b11111000 !
b11111000 ,
b11100000 #
b11100000 '
#110
b1100 !
b1100 ,
b11 %
b11 *
b11001 $
b11001 (
b1100100 #
b1100100 '
#120
b1111101 !
b1111101 ,
b0 &
b0 )
#130
b1001011 !
b1001011 ,
b1 &
b1 )
#140
b0 !
b0 ,
b10 &
b10 )
#150
b1111101 !
b1111101 ,
b11 &
b11 )
#160
b10011011 !
b10011011 ,
b100 &
b100 )
#170
b1111101 !
b1111101 ,
b101 &
b101 )
#180
b1100 !
b1100 ,
b110 &
b110 )
#190
b100000 !
b100000 ,
b111 &
b111 )
#200
b1100 !
b1100 ,
b1000 &
b1000 )
