enum_adv/enum_fsm_counter.sv
package fsm_pkg;
    typedef enum logic [1:0] {IDLE, LOAD, COUNT} state_t;
endpackage

module enum_fsm_counter 
import fsm_pkg::*;
(
    input  logic clk,
    input  logic rst_n,
    input  logic start,
    output logic [3:0] count_value,
    output logic done
);
    // Removed "logic [3:0] count = 1111" (Bad synthesis style)
    logic [3:0] count; 

    state_t current_state, next_state;

    // --- BLOCK 1: State Memory (OWNS current_state) ---
    always_ff @(posedge clk) begin 
        if(!rst_n )
            current_state <= IDLE;
        else
            current_state <= next_state;
    end

    // --- BLOCK 2: Next State Logic ---
    always_comb begin 
        // Good habit: Default next_state
        next_state = current_state; 
        
        case(current_state)
            IDLE:  if(start) next_state = LOAD; else next_state = IDLE;
            LOAD:  next_state = COUNT;
            COUNT: if(count == 0) next_state = IDLE; else next_state = COUNT;
            default: next_state = IDLE;
        endcase
    end

    // --- BLOCK 3: Datapath & Outputs ---
    always_ff @(posedge clk) begin
        if(!rst_n) begin
            count <= 4'd0;
            done  <= 1'b0;
        end else begin
            case(current_state)
                IDLE: begin 
                    done <= 1'b1; 
                end
                
                LOAD: begin 
                    count <= 4'd10; // FIX: Actually Load a value!
                    done  <= 1'b0; 
                end
                
                COUNT: begin 
                    count <= count - 1; 
                    done  <= 1'b0; 
                end
                
                // FIX: Removed 'default: current_state <= IDLE' (Multi-driver)
            endcase
        end
    end

    // FIX: Connect output continuously to internal counter
    assign count_value = count;

endmodule

enum_adv/tb_enum_fsm_counter.sv
module tb_enum_fsm_counter;
    import fsm_pkg::*; 

    logic clk, rst_n, start;
    logic [3:0] count_value;
    logic done;

    // Instantiate with name "u_dut"
    enum_fsm_counter u_dut (.*);  // a auto connection way to connect ports and signals of design and tb with same names.

    // --- THE MONITORING BLOCK ---
    always @(u_dut.current_state) begin
        $display("Time: %0t | State Changed to: %s | done: %0b | count: %0d", 
                 $time, 
                 u_dut.current_state.name(), // <--- HIERARCHICAL ACCESS
                 u_dut.done,
                 u_dut.count_value
        );
    end

    initial begin
        // Test Stimulus
        clk = 0; rst_n = 0; start = 0;
        #15 rst_n = 1;
        #10 start = 1;
        #10 start = 0;
        #400 start = 1;
        #10 start = 0;
        #10000 $finish;
    end

    initial begin
        $dumpfile("tb_enum_fsm_counter.vcd");
        $dumpvars(0, tb_enum_fsm_counter);
    end
    
    always #5 clk = ~clk;

endmodule

enum_adv/tb_enum_fsm_counter.vcd
$date
	Fri Jan  2 10:00:54 2026
$end
$version
	Icarus Verilog
$end
$timescale
	1s
$end
$scope module tb_enum_fsm_counter $end
$var wire 1 ! done $end
$var wire 4 " count_value [3:0] $end
$var reg 1 # clk $end
$var reg 1 $ rst_n $end
$var reg 1 % start $end
$scope module u_dut $end
$var wire 1 # clk $end
$var wire 4 & count_value [3:0] $end
$var wire 1 $ rst_n $end
$var wire 1 % start $end
$var reg 4 ' count [3:0] $end
$var reg 2 ( current_state [1:0] $end
$var reg 1 ! done $end
$var reg 2 ) next_state [1:0] $end
$upscope $end
$upscope $end
$enddefinitions $end
$comment Show the parameter values. $end
$dumpall
$end
#0
$dumpvars
b0 )
bx (
bx '
bx &
0%
0$
0#
bx "
x!
$end
#5
b0 (
0!
b0 "
b0 &
b0 '
1#
#10
0#
#15
1!
1#
1$
#20
0#
#25
b1 (
b10 )
1#
1%
#30
0#
#35
0!
b1010 "
b1010 &
b1010 '
b10 (
b10 )
1#
0%
#40
0#
#45
b1001 "
b1001 &
b1001 '
1#
#50
0#
#55
b1000 "
b1000 &
b1000 '
1#
#60
0#
#65
b111 "
b111 &
b111 '
1#
#70
0#
#75
b110 "
b110 &
b110 '
1#
#80
0#
#85
b101 "
b101 &
b101 '
1#
#90
0#
#95
b100 "
b100 &
b100 '
1#
#100
0#
#105
b11 "
b11 &
b11 '
1#
#110
0#
#115
b10 "
b10 &
b10 '
1#
#120
0#
#125
b1 "
b1 &
b1 '
1#
#130
0#
#135
b0 )
b0 "
b0 &
b0 '
1#
#140
0#
#145
b0 (
b1111 "
b1111 &
b1111 '
1#
#150
0#
#155
1!
1#
